{
"meta":{"test_sets":[],"test_metrics":[],"learn_metrics":[{"best_value":"Min","name":"RMSE"}],"launch_mode":"Train","parameters":"","iteration_count":1000,"learn_sets":["learn"],"name":"experiment"},
"iterations":[
{"learn":[0.9695725033],"iteration":0,"passed_time":0.06754674086,"remaining_time":67.47919412},
{"learn":[0.9406415629],"iteration":1,"passed_time":0.07800781573,"remaining_time":38.92590005},
{"learn":[0.9154848899],"iteration":2,"passed_time":0.08479500355,"remaining_time":28.18020618},
{"learn":[0.8912154974],"iteration":3,"passed_time":0.09158919044,"remaining_time":22.80570842},
{"learn":[0.8691140231],"iteration":4,"passed_time":0.09963895228,"remaining_time":19.8281515},
{"learn":[0.8476153034],"iteration":5,"passed_time":0.1106134497,"remaining_time":18.32496149},
{"learn":[0.8273637889],"iteration":6,"passed_time":0.1161742787,"remaining_time":16.48015125},
{"learn":[0.8108205142],"iteration":7,"passed_time":0.130078321,"remaining_time":16.1297118},
{"learn":[0.7950360086],"iteration":8,"passed_time":0.1358771287,"remaining_time":14.96158162},
{"learn":[0.7802266939],"iteration":9,"passed_time":0.1458675155,"remaining_time":14.44088403},
{"learn":[0.7658917546],"iteration":10,"passed_time":0.1533280648,"remaining_time":13.78558691},
{"learn":[0.7539052471],"iteration":11,"passed_time":0.1636101832,"remaining_time":13.47057175},
{"learn":[0.7428309767],"iteration":12,"passed_time":0.169043119,"remaining_time":12.83427373},
{"learn":[0.7320449381],"iteration":13,"passed_time":0.1740127457,"remaining_time":12.25546909},
{"learn":[0.7220247681],"iteration":14,"passed_time":0.1793292069,"remaining_time":11.77595125},
{"learn":[0.7126272943],"iteration":15,"passed_time":0.1848942853,"remaining_time":11.37099855},
{"learn":[0.7046657266],"iteration":16,"passed_time":0.1912063956,"remaining_time":11.05622864},
{"learn":[0.6969220342],"iteration":17,"passed_time":0.2008967518,"remaining_time":10.9600339},
{"learn":[0.6903004785],"iteration":18,"passed_time":0.2058416917,"remaining_time":10.62793156},
{"learn":[0.6839477439],"iteration":19,"passed_time":0.2116969021,"remaining_time":10.3731482},
{"learn":[0.6772621413],"iteration":20,"passed_time":0.2175668804,"remaining_time":10.14276076},
{"learn":[0.6719843083],"iteration":21,"passed_time":0.2224946727,"remaining_time":9.89089954},
{"learn":[0.6664311993],"iteration":22,"passed_time":0.2280468428,"remaining_time":9.687033281},
{"learn":[0.6619196519],"iteration":23,"passed_time":0.2330383767,"remaining_time":9.476893986},
{"learn":[0.6581269566],"iteration":24,"passed_time":0.2379028472,"remaining_time":9.278211043},
{"learn":[0.6547326694],"iteration":25,"passed_time":0.2479124915,"remaining_time":9.287183334},
{"learn":[0.6512496643],"iteration":26,"passed_time":0.2529704966,"remaining_time":9.116307155},
{"learn":[0.6475349984],"iteration":27,"passed_time":0.2582253458,"remaining_time":8.964108434},
{"learn":[0.6448128588],"iteration":28,"passed_time":0.2653611578,"remaining_time":8.885023594},
{"learn":[0.6420811528],"iteration":29,"passed_time":0.2716599298,"remaining_time":8.783671064},
{"learn":[0.6393865961],"iteration":30,"passed_time":0.2774154532,"remaining_time":8.671470135},
{"learn":[0.636402218],"iteration":31,"passed_time":0.2990711766,"remaining_time":9.046903091},
{"learn":[0.6340790897],"iteration":32,"passed_time":0.3053114763,"remaining_time":8.946551441},
{"learn":[0.632062264],"iteration":33,"passed_time":0.3111091342,"remaining_time":8.839159517},
{"learn":[0.6302941169],"iteration":34,"passed_time":0.3272507423,"remaining_time":9.022770467},
{"learn":[0.6281057364],"iteration":35,"passed_time":0.3324162933,"remaining_time":8.901369631},
{"learn":[0.6263657261],"iteration":36,"passed_time":0.3380925771,"remaining_time":8.799544643},
{"learn":[0.6244245536],"iteration":37,"passed_time":0.3461035941,"remaining_time":8.761885724},
{"learn":[0.6227951575],"iteration":38,"passed_time":0.3512866727,"remaining_time":8.65606391},
{"learn":[0.6212580707],"iteration":39,"passed_time":0.3576531459,"remaining_time":8.583675501},
{"learn":[0.6197720713],"iteration":40,"passed_time":0.3633417581,"remaining_time":8.498652342},
{"learn":[0.6181360639],"iteration":41,"passed_time":0.3686414514,"remaining_time":8.408535964},
{"learn":[0.6166756543],"iteration":42,"passed_time":0.376951979,"remaining_time":8.389373114},
{"learn":[0.615338482],"iteration":43,"passed_time":0.382718251,"remaining_time":8.315423817},
{"learn":[0.6138887144],"iteration":44,"passed_time":0.3878951505,"remaining_time":8.231997083},
{"learn":[0.6127794182],"iteration":45,"passed_time":0.3936686716,"remaining_time":8.164345928},
{"learn":[0.6115861721],"iteration":46,"passed_time":0.3991593698,"remaining_time":8.093593179},
{"learn":[0.6107752276],"iteration":47,"passed_time":0.4044347363,"remaining_time":8.021288937},
{"learn":[0.6094496273],"iteration":48,"passed_time":0.4143273359,"remaining_time":8.041332581},
{"learn":[0.6085672672],"iteration":49,"passed_time":0.4244690728,"remaining_time":8.064912383},
{"learn":[0.6076525384],"iteration":50,"passed_time":0.4299861376,"remaining_time":8.001114599},
{"learn":[0.6069144821],"iteration":51,"passed_time":0.435642404,"remaining_time":7.942096135},
{"learn":[0.6061564824],"iteration":52,"passed_time":0.440967444,"remaining_time":7.87917301},
{"learn":[0.6053837132],"iteration":53,"passed_time":0.4466543065,"remaining_time":7.82472174},
{"learn":[0.6045430346],"iteration":54,"passed_time":0.4520152918,"remaining_time":7.766444559},
{"learn":[0.603752809],"iteration":55,"passed_time":0.4572936079,"remaining_time":7.708663677},
{"learn":[0.6029275915],"iteration":56,"passed_time":0.4629591232,"remaining_time":7.659130758},
{"learn":[0.6021295247],"iteration":57,"passed_time":0.4691461999,"remaining_time":7.619581385},
{"learn":[0.6013569678],"iteration":58,"passed_time":0.4749759436,"remaining_time":7.575463778},
{"learn":[0.600704733],"iteration":59,"passed_time":0.4831684667,"remaining_time":7.569639311},
{"learn":[0.6000199865],"iteration":60,"passed_time":0.4883535651,"remaining_time":7.517442583},
{"learn":[0.599455255],"iteration":61,"passed_time":0.4962995206,"remaining_time":7.508531456},
{"learn":[0.5985160982],"iteration":62,"passed_time":0.5016734941,"remaining_time":7.461397841},
{"learn":[0.5980229311],"iteration":63,"passed_time":0.5075041077,"remaining_time":7.422247575},
{"learn":[0.5976440583],"iteration":64,"passed_time":0.5169835316,"remaining_time":7.436609262},
{"learn":[0.5972147759],"iteration":65,"passed_time":0.5221388839,"remaining_time":7.389056327},
{"learn":[0.596566021],"iteration":66,"passed_time":0.5277231899,"remaining_time":7.34874233},
{"learn":[0.5960759656],"iteration":67,"passed_time":0.5344201395,"remaining_time":7.324699559},
{"learn":[0.5957211947],"iteration":68,"passed_time":0.5440273566,"remaining_time":7.340427087},
{"learn":[0.5951409781],"iteration":69,"passed_time":0.5496672153,"remaining_time":7.302721574},
{"learn":[0.5947290637],"iteration":70,"passed_time":0.5589953491,"remaining_time":7.314178582},
{"learn":[0.5945141848],"iteration":71,"passed_time":0.564351715,"remaining_time":7.273866548},
{"learn":[0.5938868843],"iteration":72,"passed_time":0.570734316,"remaining_time":7.247543985},
{"learn":[0.5932786118],"iteration":73,"passed_time":0.5762468413,"remaining_time":7.210872636},
{"learn":[0.5927888471],"iteration":74,"passed_time":0.58447312,"remaining_time":7.208501813},
{"learn":[0.5922297575],"iteration":75,"passed_time":0.5895639608,"remaining_time":7.167856576},
{"learn":[0.5918435957],"iteration":76,"passed_time":0.594476805,"remaining_time":7.126001182},
{"learn":[0.5915422496],"iteration":77,"passed_time":0.599953525,"remaining_time":7.091758335},
{"learn":[0.591167685],"iteration":78,"passed_time":0.6049962622,"remaining_time":7.053184272},
{"learn":[0.5907081059],"iteration":79,"passed_time":0.6109899743,"remaining_time":7.026384704},
{"learn":[0.590220351],"iteration":80,"passed_time":0.616522347,"remaining_time":6.994864654},
{"learn":[0.5898202862],"iteration":81,"passed_time":0.6217711671,"remaining_time":6.960804041},
{"learn":[0.5892388679],"iteration":82,"passed_time":0.6265814448,"remaining_time":6.922592589},
{"learn":[0.5887716636],"iteration":83,"passed_time":0.6324804993,"remaining_time":6.897049254},
{"learn":[0.588441109],"iteration":84,"passed_time":0.6372091377,"remaining_time":6.859368953},
{"learn":[0.588138061],"iteration":85,"passed_time":0.6425748124,"remaining_time":6.829225332},
{"learn":[0.5876487573],"iteration":86,"passed_time":0.6508287174,"remaining_time":6.829961138},
{"learn":[0.5871917534],"iteration":87,"passed_time":0.6577205215,"remaining_time":6.816376313},
{"learn":[0.5868274794],"iteration":88,"passed_time":0.6632740115,"remaining_time":6.789242971},
{"learn":[0.5864251581],"iteration":89,"passed_time":0.6689304979,"remaining_time":6.76363059},
{"learn":[0.5860204467],"iteration":90,"passed_time":0.6742898534,"remaining_time":6.735488755},
{"learn":[0.5857644844],"iteration":91,"passed_time":0.6844351898,"remaining_time":6.755077743},
{"learn":[0.5852631899],"iteration":92,"passed_time":0.6904224327,"remaining_time":6.733474694},
{"learn":[0.5848403201],"iteration":93,"passed_time":0.6959802522,"remaining_time":6.708064984},
{"learn":[0.5843850916],"iteration":94,"passed_time":0.702394719,"remaining_time":6.691233902},
{"learn":[0.5840627347],"iteration":95,"passed_time":0.7080327878,"remaining_time":6.667308752},
{"learn":[0.5836997435],"iteration":96,"passed_time":0.717807063,"remaining_time":6.682265751},
{"learn":[0.5834852126],"iteration":97,"passed_time":0.7228077656,"remaining_time":6.65278168},
{"learn":[0.5833019496],"iteration":98,"passed_time":0.7276256323,"remaining_time":6.62212823},
{"learn":[0.5829047423],"iteration":99,"passed_time":0.7335908482,"remaining_time":6.602317634},
{"learn":[0.5822566968],"iteration":100,"passed_time":0.7384088548,"remaining_time":6.572569906},
{"learn":[0.5818817039],"iteration":101,"passed_time":0.7436834515,"remaining_time":6.547330779},
{"learn":[0.5812132851],"iteration":102,"passed_time":0.748533204,"remaining_time":6.518779456},
{"learn":[0.5807927527],"iteration":103,"passed_time":0.7536872865,"remaining_time":6.493305853},
{"learn":[0.5804188344],"iteration":104,"passed_time":0.758886513,"remaining_time":6.468604087},
{"learn":[0.5797014375],"iteration":105,"passed_time":0.7635440808,"remaining_time":6.439701964},
{"learn":[0.5794090653],"iteration":106,"passed_time":0.7774516926,"remaining_time":6.488451977},
{"learn":[0.578938203],"iteration":107,"passed_time":0.7847176475,"remaining_time":6.481186496},
{"learn":[0.5785746038],"iteration":108,"passed_time":0.7901363052,"remaining_time":6.458820623},
{"learn":[0.5780543467],"iteration":109,"passed_time":0.7952124679,"remaining_time":6.433991786},
{"learn":[0.5777919438],"iteration":110,"passed_time":0.8034855804,"remaining_time":6.435123252},
{"learn":[0.5773754622],"iteration":111,"passed_time":0.8081855226,"remaining_time":6.407756643},
{"learn":[0.5771097691],"iteration":112,"passed_time":0.8133720008,"remaining_time":6.384610307},
{"learn":[0.5770341088],"iteration":113,"passed_time":0.8235819987,"remaining_time":6.400821499},
{"learn":[0.5767065567],"iteration":114,"passed_time":0.828448399,"remaining_time":6.375450723},
{"learn":[0.5761054826],"iteration":115,"passed_time":0.8348652355,"remaining_time":6.362248864},
{"learn":[0.5758922366],"iteration":116,"passed_time":0.8407703792,"remaining_time":6.345301238},
{"learn":[0.5755179719],"iteration":117,"passed_time":0.8471125956,"remaining_time":6.331807706},
{"learn":[0.5752319613],"iteration":118,"passed_time":0.8555416775,"remaining_time":6.333884184},
{"learn":[0.5749231332],"iteration":119,"passed_time":0.8612148318,"remaining_time":6.315575433},
{"learn":[0.5746903735],"iteration":120,"passed_time":0.8663137915,"remaining_time":6.29330432},
{"learn":[0.5744266623],"iteration":121,"passed_time":0.87119417,"remaining_time":6.26974165},
{"learn":[0.5741734592],"iteration":122,"passed_time":0.876541707,"remaining_time":6.249813635},
{"learn":[0.5740385433],"iteration":123,"passed_time":0.8816549449,"remaining_time":6.228465578},
{"learn":[0.5738803625],"iteration":124,"passed_time":0.8896151485,"remaining_time":6.22730604},
{"learn":[0.5735653566],"iteration":125,"passed_time":0.8942565984,"remaining_time":6.203017992},
{"learn":[0.5732266952],"iteration":126,"passed_time":0.8992457026,"remaining_time":6.181429121},
{"learn":[0.5730343802],"iteration":127,"passed_time":0.9045334475,"remaining_time":6.162134111},
{"learn":[0.5725700064],"iteration":128,"passed_time":0.9102612845,"remaining_time":6.146027743},
{"learn":[0.5723992561],"iteration":129,"passed_time":0.9168414296,"remaining_time":6.135784952},
{"learn":[0.5720964583],"iteration":130,"passed_time":0.9222804246,"remaining_time":6.11802816},
{"learn":[0.5718939564],"iteration":131,"passed_time":0.9293707526,"remaining_time":6.111316767},
{"learn":[0.5716378759],"iteration":132,"passed_time":0.9342773376,"remaining_time":6.090364298},
{"learn":[0.5713635007],"iteration":133,"passed_time":0.9394112527,"remaining_time":6.071120484},
{"learn":[0.5710497439],"iteration":134,"passed_time":0.9449852,"remaining_time":6.054905171},
{"learn":[0.5705183922],"iteration":135,"passed_time":0.9504660996,"remaining_time":6.038255221},
{"learn":[0.5701899558],"iteration":136,"passed_time":0.956122676,"remaining_time":6.022874959},
{"learn":[0.5699397247],"iteration":137,"passed_time":0.9807814345,"remaining_time":6.12633041},
{"learn":[0.5695017258],"iteration":138,"passed_time":0.9860131268,"remaining_time":6.107606491},
{"learn":[0.5693585533],"iteration":139,"passed_time":0.9915557382,"remaining_time":6.090985249},
{"learn":[0.5691051199],"iteration":140,"passed_time":0.9975268833,"remaining_time":6.077131864},
{"learn":[0.5690404926],"iteration":141,"passed_time":1.002473423,"remaining_time":6.057198571},
{"learn":[0.568839943],"iteration":142,"passed_time":1.008406793,"remaining_time":6.043388963},
{"learn":[0.568742915],"iteration":143,"passed_time":1.013933367,"remaining_time":6.027270569},
{"learn":[0.5683334095],"iteration":144,"passed_time":1.019271915,"remaining_time":6.010189567},
{"learn":[0.5679533714],"iteration":145,"passed_time":1.025557359,"remaining_time":5.998808112},
{"learn":[0.5675880453],"iteration":146,"passed_time":1.030810888,"remaining_time":5.981508078},
{"learn":[0.5673872559],"iteration":147,"passed_time":1.036487842,"remaining_time":5.966808387},
{"learn":[0.5668226023],"iteration":148,"passed_time":1.041803043,"remaining_time":5.950163689},
{"learn":[0.5666301119],"iteration":149,"passed_time":1.046517143,"remaining_time":5.930263813},
{"learn":[0.5663146146],"iteration":150,"passed_time":1.051630931,"remaining_time":5.912812322},
{"learn":[0.5660003011],"iteration":151,"passed_time":1.056744039,"remaining_time":5.895519376},
{"learn":[0.5656312838],"iteration":152,"passed_time":1.062274632,"remaining_time":5.88069682},
{"learn":[0.5652864997],"iteration":153,"passed_time":1.066924701,"remaining_time":5.861157772},
{"learn":[0.5647260011],"iteration":154,"passed_time":1.071945471,"remaining_time":5.843831761},
{"learn":[0.5644382694],"iteration":155,"passed_time":1.077118971,"remaining_time":5.827489816},
{"learn":[0.5638606974],"iteration":156,"passed_time":1.08214555,"remaining_time":5.810501266},
{"learn":[0.5636712599],"iteration":157,"passed_time":1.08701445,"remaining_time":5.792823841},
{"learn":[0.5633971306],"iteration":158,"passed_time":1.09180365,"remaining_time":5.774885975},
{"learn":[0.5631166099],"iteration":159,"passed_time":1.096805093,"remaining_time":5.758226738},
{"learn":[0.5628292862],"iteration":160,"passed_time":1.103626606,"remaining_time":5.751197035},
{"learn":[0.5626510171],"iteration":161,"passed_time":1.108022748,"remaining_time":5.731623847},
{"learn":[0.5623745628],"iteration":162,"passed_time":1.113959218,"remaining_time":5.720146414},
{"learn":[0.5622186643],"iteration":163,"passed_time":1.118423841,"remaining_time":5.701233727},
{"learn":[0.5619243663],"iteration":164,"passed_time":1.123666122,"remaining_time":5.686431588},
{"learn":[0.5615264517],"iteration":165,"passed_time":1.128801747,"remaining_time":5.671208777},
{"learn":[0.561145445],"iteration":166,"passed_time":1.134736947,"remaining_time":5.66009507},
{"learn":[0.5609749243],"iteration":167,"passed_time":1.139557573,"remaining_time":5.643523219},
{"learn":[0.5606411569],"iteration":168,"passed_time":1.145123671,"remaining_time":5.630756041},
{"learn":[0.5598166247],"iteration":169,"passed_time":1.150097608,"remaining_time":5.615182437},
{"learn":[0.5594462526],"iteration":170,"passed_time":1.157335916,"remaining_time":5.610710377},
{"learn":[0.5590385226],"iteration":171,"passed_time":1.162458593,"remaining_time":5.596021598},
{"learn":[0.5586121007],"iteration":172,"passed_time":1.167155475,"remaining_time":5.579407966},
{"learn":[0.5579419417],"iteration":173,"passed_time":1.173372278,"remaining_time":5.570146562},
{"learn":[0.5575054536],"iteration":174,"passed_time":1.182803438,"remaining_time":5.576073352},
{"learn":[0.5568447548],"iteration":175,"passed_time":1.191641357,"remaining_time":5.57904817},
{"learn":[0.5565399603],"iteration":176,"passed_time":1.198052274,"remaining_time":5.570604641},
{"learn":[0.5562313166],"iteration":177,"passed_time":1.208625554,"remaining_time":5.581405648},
{"learn":[0.5559128474],"iteration":178,"passed_time":1.21352443,"remaining_time":5.56594166},
{"learn":[0.5556445231],"iteration":179,"passed_time":1.218749533,"remaining_time":5.552081207},
{"learn":[0.5551812369],"iteration":180,"passed_time":1.22425226,"remaining_time":5.53957238},
{"learn":[0.5545418519],"iteration":181,"passed_time":1.230676905,"remaining_time":5.531284113},
{"learn":[0.5541908852],"iteration":182,"passed_time":1.236306525,"remaining_time":5.519466837},
{"learn":[0.5538143331],"iteration":183,"passed_time":1.244504758,"remaining_time":5.519108056},
{"learn":[0.5535380236],"iteration":184,"passed_time":1.249554274,"remaining_time":5.504793153},
{"learn":[0.5532989158],"iteration":185,"passed_time":1.254566475,"remaining_time":5.490414573},
{"learn":[0.5530109581],"iteration":186,"passed_time":1.261037054,"remaining_time":5.482476606},
{"learn":[0.5525800543],"iteration":187,"passed_time":1.267583654,"remaining_time":5.47488259},
{"learn":[0.5523316843],"iteration":188,"passed_time":1.273635458,"remaining_time":5.465176491},
{"learn":[0.5521237141],"iteration":189,"passed_time":1.278713641,"remaining_time":5.451358153},
{"learn":[0.5518842523],"iteration":190,"passed_time":1.284163524,"remaining_time":5.439205713},
{"learn":[0.5514112845],"iteration":191,"passed_time":1.292955069,"remaining_time":5.441185914},
{"learn":[0.5511131216],"iteration":192,"passed_time":1.298127879,"remaining_time":5.427923307},
{"learn":[0.5507982809],"iteration":193,"passed_time":1.303622077,"remaining_time":5.416079349},
{"learn":[0.5504777793],"iteration":194,"passed_time":1.318008905,"remaining_time":5.441011122},
{"learn":[0.5502765656],"iteration":195,"passed_time":1.323210272,"remaining_time":5.427862543},
{"learn":[0.5498007868],"iteration":196,"passed_time":1.329063092,"remaining_time":5.417450067},
{"learn":[0.549441646],"iteration":197,"passed_time":1.335030548,"remaining_time":5.407547977},
{"learn":[0.5492168829],"iteration":198,"passed_time":1.340828606,"remaining_time":5.397003584},
{"learn":[0.5489945251],"iteration":199,"passed_time":1.350087559,"remaining_time":5.400350234},
{"learn":[0.5483854597],"iteration":200,"passed_time":1.355677074,"remaining_time":5.388984985},
{"learn":[0.548284955],"iteration":201,"passed_time":1.360305455,"remaining_time":5.373879968},
{"learn":[0.5481007759],"iteration":202,"passed_time":1.365739361,"remaining_time":5.362040743},
{"learn":[0.547930609],"iteration":203,"passed_time":1.371557306,"remaining_time":5.351762823},
{"learn":[0.5474490622],"iteration":204,"passed_time":1.377395559,"remaining_time":5.341607168},
{"learn":[0.5472496078],"iteration":205,"passed_time":1.382430117,"remaining_time":5.328395694},
{"learn":[0.5470519111],"iteration":206,"passed_time":1.390416977,"remaining_time":5.326573251},
{"learn":[0.546939661],"iteration":207,"passed_time":1.395589517,"remaining_time":5.31397547},
{"learn":[0.5467596378],"iteration":208,"passed_time":1.400682788,"remaining_time":5.301148733},
{"learn":[0.5461231692],"iteration":209,"passed_time":1.406248286,"remaining_time":5.290172124},
{"learn":[0.5458803381],"iteration":210,"passed_time":1.411139203,"remaining_time":5.276724319},
{"learn":[0.5456985828],"iteration":211,"passed_time":1.416156944,"remaining_time":5.26382864},
{"learn":[0.545268516],"iteration":212,"passed_time":1.421556364,"remaining_time":5.252417176},
{"learn":[0.5446760046],"iteration":213,"passed_time":1.427499853,"remaining_time":5.243060206},
{"learn":[0.544484804],"iteration":214,"passed_time":1.432443083,"remaining_time":5.230082884},
{"learn":[0.5443144636],"iteration":215,"passed_time":1.437417849,"remaining_time":5.217294414},
{"learn":[0.5442247044],"iteration":216,"passed_time":1.442059669,"remaining_time":5.203376593},
{"learn":[0.5438238574],"iteration":217,"passed_time":1.447994679,"remaining_time":5.194182746},
{"learn":[0.5437314197],"iteration":218,"passed_time":1.453075511,"remaining_time":5.181972483},
{"learn":[0.5434819203],"iteration":219,"passed_time":1.458444255,"remaining_time":5.170847813},
{"learn":[0.5432508637],"iteration":220,"passed_time":1.463598087,"remaining_time":5.159017693},
{"learn":[0.5427886875],"iteration":221,"passed_time":1.469031683,"remaining_time":5.148228151},
{"learn":[0.5425694491],"iteration":222,"passed_time":1.474339385,"remaining_time":5.137047993},
{"learn":[0.5424383065],"iteration":223,"passed_time":1.479340598,"remaining_time":5.1248585},
{"learn":[0.5421107305],"iteration":224,"passed_time":1.484864292,"remaining_time":5.114532561},
{"learn":[0.541902948],"iteration":225,"passed_time":1.490004966,"remaining_time":5.102937362},
{"learn":[0.5413703324],"iteration":226,"passed_time":1.494794667,"remaining_time":5.090203865},
{"learn":[0.5411006992],"iteration":227,"passed_time":1.50937123,"remaining_time":5.110678026},
{"learn":[0.5409258368],"iteration":228,"passed_time":1.513951638,"remaining_time":5.097190887},
{"learn":[0.5404735972],"iteration":229,"passed_time":1.52002714,"remaining_time":5.088786511},
{"learn":[0.5402379294],"iteration":230,"passed_time":1.525531726,"remaining_time":5.07850172},
{"learn":[0.5400249921],"iteration":231,"passed_time":1.530822661,"remaining_time":5.067550877},
{"learn":[0.5397060773],"iteration":232,"passed_time":1.536466379,"remaining_time":5.057809925},
{"learn":[0.5395213021],"iteration":233,"passed_time":1.542436614,"remaining_time":5.049172847},
{"learn":[0.5393858342],"iteration":234,"passed_time":1.548299453,"remaining_time":5.040208859},
{"learn":[0.539279738],"iteration":235,"passed_time":1.553532275,"remaining_time":5.029231604},
{"learn":[0.5390063172],"iteration":236,"passed_time":1.558529129,"remaining_time":5.017543144},
{"learn":[0.5387619007],"iteration":237,"passed_time":1.564118024,"remaining_time":5.007806446},
{"learn":[0.5383799899],"iteration":238,"passed_time":1.570896783,"remaining_time":5.001893104},
{"learn":[0.5381448397],"iteration":239,"passed_time":1.576379682,"remaining_time":4.991868993},
{"learn":[0.5379513457],"iteration":240,"passed_time":1.581513897,"remaining_time":4.980784431},
{"learn":[0.5371385762],"iteration":241,"passed_time":1.586998406,"remaining_time":4.970846248},
{"learn":[0.5367095841],"iteration":242,"passed_time":1.59206786,"remaining_time":4.959651728},
{"learn":[0.5364924479],"iteration":243,"passed_time":1.597354195,"remaining_time":4.949179391},
{"learn":[0.5359170601],"iteration":244,"passed_time":1.607656721,"remaining_time":4.954207445},
{"learn":[0.5355380404],"iteration":245,"passed_time":1.626480026,"remaining_time":4.985227398},
{"learn":[0.5353459041],"iteration":246,"passed_time":1.631310201,"remaining_time":4.973184541},
{"learn":[0.535024181],"iteration":247,"passed_time":1.636614574,"remaining_time":4.962637741},
{"learn":[0.5348557613],"iteration":248,"passed_time":1.641534807,"remaining_time":4.950974459},
{"learn":[0.5344630552],"iteration":249,"passed_time":1.647545317,"remaining_time":4.942635952},
{"learn":[0.5343214748],"iteration":250,"passed_time":1.652342307,"remaining_time":4.930694772},
{"learn":[0.5341124962],"iteration":251,"passed_time":1.657431258,"remaining_time":4.919676908},
{"learn":[0.5337055127],"iteration":252,"passed_time":1.662594409,"remaining_time":4.908924994},
{"learn":[0.5334716842],"iteration":253,"passed_time":1.667700768,"remaining_time":4.898050286},
{"learn":[0.5332568055],"iteration":254,"passed_time":1.673710388,"remaining_time":4.88985976},
{"learn":[0.5331316773],"iteration":255,"passed_time":1.683485733,"remaining_time":4.892630411},
{"learn":[0.5328703013],"iteration":256,"passed_time":1.689107524,"remaining_time":4.883295293},
{"learn":[0.5325944643],"iteration":257,"passed_time":1.694346485,"remaining_time":4.872887953},
{"learn":[0.5325174937],"iteration":258,"passed_time":1.699552981,"remaining_time":4.86242764},
{"learn":[0.5322341708],"iteration":259,"passed_time":1.704865862,"remaining_time":4.852310531},
{"learn":[0.5318858039],"iteration":260,"passed_time":1.709935536,"remaining_time":4.841541613},
{"learn":[0.5317565867],"iteration":261,"passed_time":1.715159789,"remaining_time":4.83125162},
{"learn":[0.5313602263],"iteration":262,"passed_time":1.720749594,"remaining_time":4.822024529},
{"learn":[0.5311175778],"iteration":263,"passed_time":1.725927304,"remaining_time":4.81167612},
{"learn":[0.5308758981],"iteration":264,"passed_time":1.731318235,"remaining_time":4.801958124},
{"learn":[0.5306309513],"iteration":265,"passed_time":1.736816422,"remaining_time":4.792568624},
{"learn":[0.5304454327],"iteration":266,"passed_time":1.742103007,"remaining_time":4.782627358},
{"learn":[0.5299747499],"iteration":267,"passed_time":1.74726012,"remaining_time":4.772367192},
{"learn":[0.5297726506],"iteration":268,"passed_time":1.75258212,"remaining_time":4.762593047},
{"learn":[0.5296327182],"iteration":269,"passed_time":1.757444501,"remaining_time":4.751609206},
{"learn":[0.5292491652],"iteration":270,"passed_time":1.762486518,"remaining_time":4.74115377},
{"learn":[0.5289083602],"iteration":271,"passed_time":1.76741778,"remaining_time":4.730441705},
{"learn":[0.5288035008],"iteration":272,"passed_time":1.77258741,"remaining_time":4.720406766},
{"learn":[0.5285058019],"iteration":273,"passed_time":1.777960194,"remaining_time":4.710945623},
{"learn":[0.5282132546],"iteration":274,"passed_time":1.784630357,"remaining_time":4.704934578},
{"learn":[0.5280019243],"iteration":275,"passed_time":1.789285855,"remaining_time":4.69363391},
{"learn":[0.5277815186],"iteration":276,"passed_time":1.798293251,"remaining_time":4.693740147},
{"learn":[0.5277117666],"iteration":277,"passed_time":1.809424848,"remaining_time":4.699297627},
{"learn":[0.5275307809],"iteration":278,"passed_time":1.815444527,"remaining_time":4.691525103},
{"learn":[0.5271666391],"iteration":279,"passed_time":1.821339582,"remaining_time":4.683444639},
{"learn":[0.5269196329],"iteration":280,"passed_time":1.826765858,"remaining_time":4.674180257},
{"learn":[0.5262978694],"iteration":281,"passed_time":1.83276195,"remaining_time":4.666393902},
{"learn":[0.5260083607],"iteration":282,"passed_time":1.838296603,"remaining_time":4.65745111},
{"learn":[0.5257133732],"iteration":283,"passed_time":1.843860581,"remaining_time":4.648606254},
{"learn":[0.5254060688],"iteration":284,"passed_time":1.84896459,"remaining_time":4.638630463},
{"learn":[0.525146388],"iteration":285,"passed_time":1.854156428,"remaining_time":4.628908005},
{"learn":[0.5250347324],"iteration":286,"passed_time":1.859357984,"remaining_time":4.619241264},
{"learn":[0.5248910974],"iteration":287,"passed_time":1.864337989,"remaining_time":4.609057807},
{"learn":[0.5245208716],"iteration":288,"passed_time":1.869473584,"remaining_time":4.599293144},
{"learn":[0.5242546783],"iteration":289,"passed_time":1.875251775,"remaining_time":4.591133656},
{"learn":[0.5240851536],"iteration":290,"passed_time":1.880363763,"remaining_time":4.581367381},
{"learn":[0.5239384826],"iteration":291,"passed_time":1.885337339,"remaining_time":4.571297384},
{"learn":[0.5235314487],"iteration":292,"passed_time":1.89042987,"remaining_time":4.561549208},
{"learn":[0.5229935808],"iteration":293,"passed_time":1.89628641,"remaining_time":4.553667365},
{"learn":[0.522846335],"iteration":294,"passed_time":1.904106712,"remaining_time":4.550492311},
{"learn":[0.5224844391],"iteration":295,"passed_time":1.909181245,"remaining_time":4.540755393},
{"learn":[0.5221471391],"iteration":296,"passed_time":1.91773913,"remaining_time":4.539294977},
{"learn":[0.5218643601],"iteration":297,"passed_time":1.92313876,"remaining_time":4.530347012},
{"learn":[0.5216794478],"iteration":298,"passed_time":1.928331007,"remaining_time":4.520936576},
{"learn":[0.5213708243],"iteration":299,"passed_time":1.934645477,"remaining_time":4.514172781},
{"learn":[0.5212186152],"iteration":300,"passed_time":1.94055876,"remaining_time":4.50648031},
{"learn":[0.5209999566],"iteration":301,"passed_time":1.945738459,"remaining_time":4.497104121},
{"learn":[0.5208621816],"iteration":302,"passed_time":1.951246965,"remaining_time":4.488511996},
{"learn":[0.5207135313],"iteration":303,"passed_time":1.957209741,"remaining_time":4.480980197},
{"learn":[0.5204202746],"iteration":304,"passed_time":1.9627702,"remaining_time":4.472541932},
{"learn":[0.5202668452],"iteration":305,"passed_time":1.968317661,"remaining_time":4.464092996},
{"learn":[0.5199246633],"iteration":306,"passed_time":1.974464983,"remaining_time":4.457017047},
{"learn":[0.5195645455],"iteration":307,"passed_time":1.980678906,"remaining_time":4.450096763},
{"learn":[0.519404928],"iteration":308,"passed_time":1.986673158,"remaining_time":4.442689814},
{"learn":[0.5191770733],"iteration":309,"passed_time":1.991937346,"remaining_time":4.433666997},
{"learn":[0.5189577358],"iteration":310,"passed_time":1.997062453,"remaining_time":4.424360225},
{"learn":[0.5186741545],"iteration":311,"passed_time":2.002763083,"remaining_time":4.416349363},
{"learn":[0.5184801305],"iteration":312,"passed_time":2.007693225,"remaining_time":4.406662127},
{"learn":[0.5182601521],"iteration":313,"passed_time":2.013126601,"remaining_time":4.398104612},
{"learn":[0.5180203526],"iteration":314,"passed_time":2.021213098,"remaining_time":4.395336419},
{"learn":[0.5179366038],"iteration":315,"passed_time":2.026121703,"remaining_time":4.385655838},
{"learn":[0.5174982067],"iteration":316,"passed_time":2.031094459,"remaining_time":4.376143582},
{"learn":[0.517251731],"iteration":317,"passed_time":2.036302974,"remaining_time":4.367165498},
{"learn":[0.5167769011],"iteration":318,"passed_time":2.041749758,"remaining_time":4.358719704},
{"learn":[0.5165710977],"iteration":319,"passed_time":2.047052321,"remaining_time":4.349986183},
{"learn":[0.5164521225],"iteration":320,"passed_time":2.051963406,"remaining_time":4.340445958},
{"learn":[0.5161776964],"iteration":321,"passed_time":2.057321641,"remaining_time":4.331876003},
{"learn":[0.5159950714],"iteration":322,"passed_time":2.062526107,"remaining_time":4.323003637},
{"learn":[0.5155840273],"iteration":323,"passed_time":2.0675286,"remaining_time":4.313732511},
{"learn":[0.5152561878],"iteration":324,"passed_time":2.073253167,"remaining_time":4.305987347},
{"learn":[0.5149107645],"iteration":325,"passed_time":2.079064033,"remaining_time":4.298433001},
{"learn":[0.514730808],"iteration":326,"passed_time":2.084923413,"remaining_time":4.290989165},
{"learn":[0.5146075951],"iteration":327,"passed_time":2.090098903,"remaining_time":4.28215385},
{"learn":[0.5144793954],"iteration":328,"passed_time":2.09491228,"remaining_time":4.272602249},
{"learn":[0.514124339],"iteration":329,"passed_time":2.100118526,"remaining_time":4.263877007},
{"learn":[0.5140440342],"iteration":330,"passed_time":2.105382074,"remaining_time":4.255288844},
{"learn":[0.5138496216],"iteration":331,"passed_time":2.110228577,"remaining_time":4.245881594},
{"learn":[0.5137297213],"iteration":332,"passed_time":2.115781707,"remaining_time":4.237917112},
{"learn":[0.5135145569],"iteration":333,"passed_time":2.12176509,"remaining_time":4.230825},
{"learn":[0.5132251209],"iteration":334,"passed_time":2.126719159,"remaining_time":4.221696241},
{"learn":[0.5127619413],"iteration":335,"passed_time":2.136288201,"remaining_time":4.221712397},
{"learn":[0.512483402],"iteration":336,"passed_time":2.144031683,"remaining_time":4.218080136},
{"learn":[0.5121796696],"iteration":337,"passed_time":2.149994949,"remaining_time":4.210936853},
{"learn":[0.5119894241],"iteration":338,"passed_time":2.156523621,"remaining_time":4.20490299},
{"learn":[0.5116751506],"iteration":339,"passed_time":2.162765121,"remaining_time":4.198308764},
{"learn":[0.5115527261],"iteration":340,"passed_time":2.16908595,"remaining_time":4.191869915},
{"learn":[0.5114246178],"iteration":341,"passed_time":2.174684354,"remaining_time":4.184041827},
{"learn":[0.511341217],"iteration":342,"passed_time":2.179898438,"remaining_time":4.175490595},
{"learn":[0.5110692615],"iteration":343,"passed_time":2.190514693,"remaining_time":4.177260577},
{"learn":[0.5107251118],"iteration":344,"passed_time":2.195866519,"remaining_time":4.168963972},
{"learn":[0.5105694138],"iteration":345,"passed_time":2.205603889,"remaining_time":4.168973826},
{"learn":[0.5101910414],"iteration":346,"passed_time":2.210626189,"remaining_time":4.160054471},
{"learn":[0.5098890168],"iteration":347,"passed_time":2.215707821,"remaining_time":4.151268677},
{"learn":[0.5097591045],"iteration":348,"passed_time":2.222591256,"remaining_time":4.145865066},
{"learn":[0.5094624811],"iteration":349,"passed_time":2.232927958,"remaining_time":4.146866207},
{"learn":[0.5091217512],"iteration":350,"passed_time":2.240428692,"remaining_time":4.142559034},
{"learn":[0.5088287339],"iteration":351,"passed_time":2.246036475,"remaining_time":4.134748964},
{"learn":[0.5084686818],"iteration":352,"passed_time":2.251867068,"remaining_time":4.127359754},
{"learn":[0.5081144229],"iteration":353,"passed_time":2.258389111,"remaining_time":4.121241146},
{"learn":[0.5078425531],"iteration":354,"passed_time":2.263828136,"remaining_time":4.113152528},
{"learn":[0.5076427716],"iteration":355,"passed_time":2.269938273,"remaining_time":4.10629283},
{"learn":[0.5074187781],"iteration":356,"passed_time":2.275516359,"remaining_time":4.098479045},
{"learn":[0.5073021864],"iteration":357,"passed_time":2.281834779,"remaining_time":4.092005385},
{"learn":[0.5070425174],"iteration":358,"passed_time":2.290642601,"remaining_time":4.089977457},
{"learn":[0.5068390988],"iteration":359,"passed_time":2.295621716,"remaining_time":4.081105274},
{"learn":[0.5065157638],"iteration":360,"passed_time":2.323114562,"remaining_time":4.112105832},
{"learn":[0.5061837535],"iteration":361,"passed_time":2.330262813,"remaining_time":4.106927278},
{"learn":[0.5058965053],"iteration":362,"passed_time":2.335552268,"remaining_time":4.098476018},
{"learn":[0.5057696977],"iteration":363,"passed_time":2.341203925,"remaining_time":4.090674989},
{"learn":[0.5056451976],"iteration":364,"passed_time":2.347048656,"remaining_time":4.083221635},
{"learn":[0.5053827172],"iteration":365,"passed_time":2.352436728,"remaining_time":4.074986026},
{"learn":[0.5052423977],"iteration":366,"passed_time":2.357356291,"remaining_time":4.065957854},
{"learn":[0.5049625285],"iteration":367,"passed_time":2.363575684,"remaining_time":4.059184327},
{"learn":[0.5046835114],"iteration":368,"passed_time":2.373975307,"remaining_time":4.05956211},
{"learn":[0.5045190063],"iteration":369,"passed_time":2.379010985,"remaining_time":4.050748434},
{"learn":[0.5044089563],"iteration":370,"passed_time":2.393646761,"remaining_time":4.058231301},
{"learn":[0.5042275333],"iteration":371,"passed_time":2.399264842,"remaining_time":4.050371831},
{"learn":[0.503876602],"iteration":372,"passed_time":2.404040285,"remaining_time":4.041107932},
{"learn":[0.5034027114],"iteration":373,"passed_time":2.408932682,"remaining_time":4.032063793},
{"learn":[0.503251835],"iteration":374,"passed_time":2.413622255,"remaining_time":4.022703758},
{"learn":[0.5031197467],"iteration":375,"passed_time":2.418842669,"remaining_time":4.014249536},
{"learn":[0.5028968011],"iteration":376,"passed_time":2.424217522,"remaining_time":4.006067683},
{"learn":[0.5026217278],"iteration":377,"passed_time":2.435090763,"remaining_time":4.006948293},
{"learn":[0.5024025234],"iteration":378,"passed_time":2.439940685,"remaining_time":3.997897535},
{"learn":[0.5022050117],"iteration":379,"passed_time":2.444842131,"remaining_time":3.988952951},
{"learn":[0.5019050132],"iteration":380,"passed_time":2.449981656,"remaining_time":3.980416391},
{"learn":[0.501688841],"iteration":381,"passed_time":2.454428031,"remaining_time":3.970776239},
{"learn":[0.5013371742],"iteration":382,"passed_time":2.460224799,"remaining_time":3.963338645},
{"learn":[0.501210239],"iteration":383,"passed_time":2.466081739,"remaining_time":3.956006123},
{"learn":[0.5009553702],"iteration":384,"passed_time":2.471431076,"remaining_time":3.94787042},
{"learn":[0.5006951032],"iteration":385,"passed_time":2.476788752,"remaining_time":3.939762419},
{"learn":[0.5004450946],"iteration":386,"passed_time":2.482942673,"remaining_time":3.932929867},
{"learn":[0.500213409],"iteration":387,"passed_time":2.491433387,"remaining_time":3.929786682},
{"learn":[0.5001579576],"iteration":388,"passed_time":2.495784705,"remaining_time":3.920114279},
{"learn":[0.4999216614],"iteration":389,"passed_time":2.501935596,"remaining_time":3.913283881},
{"learn":[0.4997334287],"iteration":390,"passed_time":2.507378151,"remaining_time":3.905353693},
{"learn":[0.4994914777],"iteration":391,"passed_time":2.512600414,"remaining_time":3.89709452},
{"learn":[0.4992057652],"iteration":392,"passed_time":2.519756224,"remaining_time":3.891837221},
{"learn":[0.4989172791],"iteration":393,"passed_time":2.52518668,"remaining_time":3.883916568},
{"learn":[0.4987010032],"iteration":394,"passed_time":2.534330388,"remaining_time":3.88169591},
{"learn":[0.4982666457],"iteration":395,"passed_time":2.539872669,"remaining_time":3.873947203},
{"learn":[0.4978393788],"iteration":396,"passed_time":2.545324083,"remaining_time":3.866071592},
{"learn":[0.4974348987],"iteration":397,"passed_time":2.553847012,"remaining_time":3.862854024},
{"learn":[0.4971790591],"iteration":398,"passed_time":2.560356767,"remaining_time":3.856577485},
{"learn":[0.4971280391],"iteration":399,"passed_time":2.565872642,"remaining_time":3.848808962},
{"learn":[0.4969275078],"iteration":400,"passed_time":2.574245471,"remaining_time":3.845319294},
{"learn":[0.4967018767],"iteration":401,"passed_time":2.579137198,"remaining_time":3.836626976},
{"learn":[0.4965680235],"iteration":402,"passed_time":2.584199102,"remaining_time":3.828205618},
{"learn":[0.4961274001],"iteration":403,"passed_time":2.591319107,"remaining_time":3.822837098},
{"learn":[0.4957599518],"iteration":404,"passed_time":2.596763681,"remaining_time":3.814998494},
{"learn":[0.4955850887],"iteration":405,"passed_time":2.602224303,"remaining_time":3.807195163},
{"learn":[0.4954068351],"iteration":406,"passed_time":2.607326542,"remaining_time":3.798881178},
{"learn":[0.4952106564],"iteration":407,"passed_time":2.613516849,"remaining_time":3.792161702},
{"learn":[0.4950330076],"iteration":408,"passed_time":2.619251995,"remaining_time":3.784787112},
{"learn":[0.4947678383],"iteration":409,"passed_time":2.625667591,"remaining_time":3.778399705},
{"learn":[0.494635107],"iteration":410,"passed_time":2.631712857,"remaining_time":3.771481442},
{"learn":[0.4946258171],"iteration":411,"passed_time":2.63602617,"remaining_time":3.762095601},
{"learn":[0.4944850312],"iteration":412,"passed_time":2.640803332,"remaining_time":3.753393597},
{"learn":[0.4943601277],"iteration":413,"passed_time":2.646287691,"remaining_time":3.745711562},
{"learn":[0.4939370647],"iteration":414,"passed_time":2.653964662,"remaining_time":3.741130909},
{"learn":[0.4936843191],"iteration":415,"passed_time":2.660197222,"remaining_time":3.734507639},
{"learn":[0.4935690353],"iteration":416,"passed_time":2.665292513,"remaining_time":3.726296247},
{"learn":[0.4933877089],"iteration":417,"passed_time":2.671026139,"remaining_time":3.718988547},
{"learn":[0.493256076],"iteration":418,"passed_time":2.676469423,"remaining_time":3.711285764},
{"learn":[0.4930141409],"iteration":419,"passed_time":2.681654422,"remaining_time":3.703237059},
{"learn":[0.4928702821],"iteration":420,"passed_time":2.686770769,"remaining_time":3.695107542},
{"learn":[0.4927593942],"iteration":421,"passed_time":2.692370953,"remaining_time":3.687655002},
{"learn":[0.4923896487],"iteration":422,"passed_time":2.69802103,"remaining_time":3.680279278},
{"learn":[0.4923291974],"iteration":423,"passed_time":2.702755368,"remaining_time":3.67166767},
{"learn":[0.4921626263],"iteration":424,"passed_time":2.708018616,"remaining_time":3.663789892},
{"learn":[0.4919705061],"iteration":425,"passed_time":2.713049685,"remaining_time":3.655611547},
{"learn":[0.491799947],"iteration":426,"passed_time":2.718006273,"remaining_time":3.647347997},
{"learn":[0.4915274647],"iteration":427,"passed_time":2.723188672,"remaining_time":3.639401683},
{"learn":[0.4914223991],"iteration":428,"passed_time":2.729572543,"remaining_time":3.633067417},
{"learn":[0.4911665459],"iteration":429,"passed_time":2.735031275,"remaining_time":3.625506574},
{"learn":[0.4910676784],"iteration":430,"passed_time":2.740368224,"remaining_time":3.617794708},
{"learn":[0.4908020432],"iteration":431,"passed_time":2.745352429,"remaining_time":3.609630045},
{"learn":[0.4905560557],"iteration":432,"passed_time":2.751002706,"remaining_time":3.602352273},
{"learn":[0.4904060135],"iteration":433,"passed_time":2.755847339,"remaining_time":3.594031322},
{"learn":[0.4901149601],"iteration":434,"passed_time":2.761413407,"remaining_time":3.586663391},
{"learn":[0.489847522],"iteration":435,"passed_time":2.766703352,"remaining_time":3.578946538},
{"learn":[0.4896245972],"iteration":436,"passed_time":2.771904658,"remaining_time":3.571126596},
{"learn":[0.4893127278],"iteration":437,"passed_time":2.781072783,"remaining_time":3.568408457},
{"learn":[0.4890296261],"iteration":438,"passed_time":2.786606856,"remaining_time":3.561016961},
{"learn":[0.4887084613],"iteration":439,"passed_time":2.791731832,"remaining_time":3.553113241},
{"learn":[0.4885894043],"iteration":440,"passed_time":2.797238888,"remaining_time":3.545706436},
{"learn":[0.4884242781],"iteration":441,"passed_time":2.803184007,"remaining_time":3.538861257},
{"learn":[0.4882983616],"iteration":442,"passed_time":2.807965108,"remaining_time":3.530556581},
{"learn":[0.4882000729],"iteration":443,"passed_time":2.813165594,"remaining_time":3.522792952},
{"learn":[0.4880292307],"iteration":444,"passed_time":2.822717359,"remaining_time":3.520467717},
{"learn":[0.487867531],"iteration":445,"passed_time":2.827493771,"remaining_time":3.512178361},
{"learn":[0.4877834694],"iteration":446,"passed_time":2.832728023,"remaining_time":3.504471133},
{"learn":[0.4874312144],"iteration":447,"passed_time":2.838183976,"remaining_time":3.497048113},
{"learn":[0.487151595],"iteration":448,"passed_time":2.843480499,"remaining_time":3.489438208},
{"learn":[0.4868198349],"iteration":449,"passed_time":2.851316329,"remaining_time":3.48494218},
{"learn":[0.4866921224],"iteration":450,"passed_time":2.856196118,"remaining_time":3.476832968},
{"learn":[0.486476462],"iteration":451,"passed_time":2.861542355,"remaining_time":3.469303563},
{"learn":[0.4861679547],"iteration":452,"passed_time":2.866489875,"remaining_time":3.461302343},
{"learn":[0.4859997502],"iteration":453,"passed_time":2.871687592,"remaining_time":3.453615474},
{"learn":[0.4858531943],"iteration":454,"passed_time":2.876932112,"remaining_time":3.445995607},
{"learn":[0.4857209953],"iteration":455,"passed_time":2.882593528,"remaining_time":3.438883507},
{"learn":[0.4855882568],"iteration":456,"passed_time":2.887538328,"remaining_time":3.430926285},
{"learn":[0.4854153284],"iteration":457,"passed_time":2.893288612,"remaining_time":3.423935432},
{"learn":[0.4850143246],"iteration":458,"passed_time":2.898868559,"remaining_time":3.416749216},
{"learn":[0.4847751213],"iteration":459,"passed_time":2.903889479,"remaining_time":3.408913736},
{"learn":[0.4846325124],"iteration":460,"passed_time":2.915436951,"remaining_time":3.408721294},
{"learn":[0.4843393448],"iteration":461,"passed_time":2.920216532,"remaining_time":3.400598473},
{"learn":[0.484094363],"iteration":462,"passed_time":2.925183969,"remaining_time":3.392707973},
{"learn":[0.4839293107],"iteration":463,"passed_time":2.93005169,"remaining_time":3.384714883},
{"learn":[0.4836542063],"iteration":464,"passed_time":2.934873706,"remaining_time":3.376682651},
{"learn":[0.4835452283],"iteration":465,"passed_time":2.939758714,"remaining_time":3.36873638},
{"learn":[0.4831443692],"iteration":466,"passed_time":2.945760375,"remaining_time":3.362077687},
{"learn":[0.4830380269],"iteration":467,"passed_time":2.954155511,"remaining_time":3.358142589},
{"learn":[0.4828794428],"iteration":468,"passed_time":2.959811798,"remaining_time":3.351087558},
{"learn":[0.4827461146],"iteration":469,"passed_time":2.965722511,"remaining_time":3.344325384},
{"learn":[0.482645204],"iteration":470,"passed_time":2.970808682,"remaining_time":3.336640749},
{"learn":[0.482367291],"iteration":471,"passed_time":2.976264725,"remaining_time":3.329380879},
{"learn":[0.4819353596],"iteration":472,"passed_time":2.982776959,"remaining_time":3.323305406},
{"learn":[0.4817109246],"iteration":473,"passed_time":2.98839389,"remaining_time":3.31623457},
{"learn":[0.4815600497],"iteration":474,"passed_time":2.993750476,"remaining_time":3.308882105},
{"learn":[0.4812502028],"iteration":475,"passed_time":2.99927623,"remaining_time":3.301724253},
{"learn":[0.4810227522],"iteration":476,"passed_time":3.005303168,"remaining_time":3.29512276},
{"learn":[0.4809380776],"iteration":477,"passed_time":3.015265238,"remaining_time":3.292821034},
{"learn":[0.4807394003],"iteration":478,"passed_time":3.022839532,"remaining_time":3.28789018},
{"learn":[0.4805120263],"iteration":479,"passed_time":3.027717001,"remaining_time":3.280026751},
{"learn":[0.4801556467],"iteration":480,"passed_time":3.034174392,"remaining_time":3.273880477},
{"learn":[0.4799652915],"iteration":481,"passed_time":3.039259784,"remaining_time":3.26625844},
{"learn":[0.4797023373],"iteration":482,"passed_time":3.044205224,"remaining_time":3.258497103},
{"learn":[0.4793536891],"iteration":483,"passed_time":3.049570169,"remaining_time":3.251194643},
{"learn":[0.4791319727],"iteration":484,"passed_time":3.054978988,"remaining_time":3.24394676},
{"learn":[0.4789814207],"iteration":485,"passed_time":3.061250223,"remaining_time":3.237618549},
{"learn":[0.4787257511],"iteration":486,"passed_time":3.068326123,"remaining_time":3.232138195},
{"learn":[0.4785328604],"iteration":487,"passed_time":3.073861435,"remaining_time":3.225034949},
{"learn":[0.4782979706],"iteration":488,"passed_time":3.080459258,"remaining_time":3.219048427},
{"learn":[0.4779684634],"iteration":489,"passed_time":3.085702199,"remaining_time":3.211649228},
{"learn":[0.4778686049],"iteration":490,"passed_time":3.090197888,"remaining_time":3.203484165},
{"learn":[0.477690384],"iteration":491,"passed_time":3.095102373,"remaining_time":3.195756109},
{"learn":[0.4775733369],"iteration":492,"passed_time":3.100154109,"remaining_time":3.18819094},
{"learn":[0.4774201934],"iteration":493,"passed_time":3.105050386,"remaining_time":3.180476711},
{"learn":[0.4773325983],"iteration":494,"passed_time":3.109844565,"remaining_time":3.172669708},
{"learn":[0.4770134226],"iteration":495,"passed_time":3.117059037,"remaining_time":3.167334183},
{"learn":[0.4768120037],"iteration":496,"passed_time":3.12274403,"remaining_time":3.160443153},
{"learn":[0.4765288668],"iteration":497,"passed_time":3.128215481,"remaining_time":3.153341709},
{"learn":[0.4763933651],"iteration":498,"passed_time":3.134028776,"remaining_time":3.146590014},
{"learn":[0.4762341393],"iteration":499,"passed_time":3.139237882,"remaining_time":3.139237882},
{"learn":[0.4761631255],"iteration":500,"passed_time":3.143701815,"remaining_time":3.131152107},
{"learn":[0.4760481302],"iteration":501,"passed_time":3.148532,"remaining_time":3.123444096},
{"learn":[0.475863989],"iteration":502,"passed_time":3.15750898,"remaining_time":3.119844857},
{"learn":[0.4757795767],"iteration":503,"passed_time":3.163278231,"remaining_time":3.113067466},
{"learn":[0.4755344812],"iteration":504,"passed_time":3.16800717,"remaining_time":3.105274355},
{"learn":[0.4753523634],"iteration":505,"passed_time":3.173694982,"remaining_time":3.098429489},
{"learn":[0.4753029327],"iteration":506,"passed_time":3.1789633,"remaining_time":3.091181276},
{"learn":[0.4750736341],"iteration":507,"passed_time":3.184884231,"remaining_time":3.084572917},
{"learn":[0.4747895473],"iteration":508,"passed_time":3.190503773,"remaining_time":3.077676527},
{"learn":[0.4745807666],"iteration":509,"passed_time":3.196300361,"remaining_time":3.070955248},
{"learn":[0.4743756128],"iteration":510,"passed_time":3.2026215,"remaining_time":3.064739557},
{"learn":[0.4740949584],"iteration":511,"passed_time":3.207921983,"remaining_time":3.05755064},
{"learn":[0.4737827514],"iteration":512,"passed_time":3.217142251,"remaining_time":3.054090207},
{"learn":[0.4735975262],"iteration":513,"passed_time":3.222031148,"remaining_time":3.046511942},
{"learn":[0.4734236026],"iteration":514,"passed_time":3.227462434,"remaining_time":3.039454914},
{"learn":[0.4731787322],"iteration":515,"passed_time":3.232796893,"remaining_time":3.032313365},
{"learn":[0.4730186474],"iteration":516,"passed_time":3.238784846,"remaining_time":3.025789324},
{"learn":[0.4728731761],"iteration":517,"passed_time":3.243855,"remaining_time":3.018413339},
{"learn":[0.4725786283],"iteration":518,"passed_time":3.248931982,"remaining_time":3.011052569},
{"learn":[0.4724809919],"iteration":519,"passed_time":3.253862624,"remaining_time":3.003565499},
{"learn":[0.4723337202],"iteration":520,"passed_time":3.259313497,"remaining_time":2.996566536},
{"learn":[0.4721476664],"iteration":521,"passed_time":3.264841781,"remaining_time":2.989644389},
{"learn":[0.4718984897],"iteration":522,"passed_time":3.270498997,"remaining_time":2.982845166},
{"learn":[0.4717198799],"iteration":523,"passed_time":3.276707441,"remaining_time":2.976551034},
{"learn":[0.4713355149],"iteration":524,"passed_time":3.287153308,"remaining_time":2.974091088},
{"learn":[0.471166849],"iteration":525,"passed_time":3.291819145,"remaining_time":2.966392157},
{"learn":[0.4709891905],"iteration":526,"passed_time":3.297686643,"remaining_time":2.959783268},
{"learn":[0.4706280748],"iteration":527,"passed_time":3.302988086,"remaining_time":2.952671168},
{"learn":[0.4702592785],"iteration":528,"passed_time":3.308230267,"remaining_time":2.945513149},
{"learn":[0.4701400169],"iteration":529,"passed_time":3.314564105,"remaining_time":2.939330432},
{"learn":[0.4700754413],"iteration":530,"passed_time":3.319870797,"remaining_time":2.932239932},
{"learn":[0.4699531616],"iteration":531,"passed_time":3.329883541,"remaining_time":2.929296047},
{"learn":[0.4697278652],"iteration":532,"passed_time":3.337512118,"remaining_time":2.924236696},
{"learn":[0.4695973187],"iteration":533,"passed_time":3.341982361,"remaining_time":2.916411573},
{"learn":[0.4694784939],"iteration":534,"passed_time":3.346670534,"remaining_time":2.908788408},
{"learn":[0.4693901215],"iteration":535,"passed_time":3.352143445,"remaining_time":2.901855519},
{"learn":[0.4689169933],"iteration":536,"passed_time":3.357775804,"remaining_time":2.895065545},
{"learn":[0.4688010673],"iteration":537,"passed_time":3.368146061,"remaining_time":2.892348476},
{"learn":[0.468613637],"iteration":538,"passed_time":3.373572398,"remaining_time":2.885374537},
{"learn":[0.4684864535],"iteration":539,"passed_time":3.378942482,"remaining_time":2.878358411},
{"learn":[0.468210869],"iteration":540,"passed_time":3.404378058,"remaining_time":2.888372512},
{"learn":[0.4680700074],"iteration":541,"passed_time":3.409722126,"remaining_time":2.881278106},
{"learn":[0.4678148145],"iteration":542,"passed_time":3.415731146,"remaining_time":2.874749786},
{"learn":[0.4676304549],"iteration":543,"passed_time":3.421401451,"remaining_time":2.867939451},
{"learn":[0.4674778262],"iteration":544,"passed_time":3.42749394,"remaining_time":2.861485766},
{"learn":[0.4671372185],"iteration":545,"passed_time":3.434213797,"remaining_time":2.855555062},
{"learn":[0.4670617962],"iteration":546,"passed_time":3.439412793,"remaining_time":2.848361966},
{"learn":[0.4668529675],"iteration":547,"passed_time":3.444385689,"remaining_time":2.840989656},
{"learn":[0.4666958248],"iteration":548,"passed_time":3.450199615,"remaining_time":2.834316988},
{"learn":[0.4665219591],"iteration":549,"passed_time":3.456000343,"remaining_time":2.827636644},
{"learn":[0.4662690393],"iteration":550,"passed_time":3.461034461,"remaining_time":2.820334797},
{"learn":[0.46612997],"iteration":551,"passed_time":3.465415525,"remaining_time":2.812511151},
{"learn":[0.4659814365],"iteration":552,"passed_time":3.469784851,"remaining_time":2.804690467},
{"learn":[0.4658634236],"iteration":553,"passed_time":3.476347768,"remaining_time":2.798648203},
{"learn":[0.465532678],"iteration":554,"passed_time":3.483391882,"remaining_time":2.792989887},
{"learn":[0.4654723704],"iteration":555,"passed_time":3.493699957,"remaining_time":2.789933059},
{"learn":[0.4652193886],"iteration":556,"passed_time":3.499284883,"remaining_time":2.783093722},
{"learn":[0.4649941341],"iteration":557,"passed_time":3.513765229,"remaining_time":2.783305074},
{"learn":[0.4648160781],"iteration":558,"passed_time":3.51900814,"remaining_time":2.776176368},
{"learn":[0.4644362013],"iteration":559,"passed_time":3.524807568,"remaining_time":2.76949166},
{"learn":[0.4641525448],"iteration":560,"passed_time":3.530323303,"remaining_time":2.76258811},
{"learn":[0.4640966046],"iteration":561,"passed_time":3.536173014,"remaining_time":2.755949787},
{"learn":[0.4638150043],"iteration":562,"passed_time":3.541356192,"remaining_time":2.748796902},
{"learn":[0.4636494346],"iteration":563,"passed_time":3.546932329,"remaining_time":2.74195478},
{"learn":[0.4633547476],"iteration":564,"passed_time":3.555211971,"remaining_time":2.737198597},
{"learn":[0.4631877055],"iteration":565,"passed_time":3.559814866,"remaining_time":2.729610692},
{"learn":[0.4628548212],"iteration":566,"passed_time":3.564356009,"remaining_time":2.721986159},
{"learn":[0.4626500132],"iteration":567,"passed_time":3.575311069,"remaining_time":2.719250672},
{"learn":[0.4625388347],"iteration":568,"passed_time":3.580862339,"remaining_time":2.71239309},
{"learn":[0.4623155867],"iteration":569,"passed_time":3.586518066,"remaining_time":2.705618892},
{"learn":[0.4620680088],"iteration":570,"passed_time":3.596054812,"remaining_time":2.701764474},
{"learn":[0.4619687984],"iteration":571,"passed_time":3.601454232,"remaining_time":2.694794426},
{"learn":[0.4615646484],"iteration":572,"passed_time":3.607005643,"remaining_time":2.687943123},
{"learn":[0.4614526787],"iteration":573,"passed_time":3.612672598,"remaining_time":2.681182102},
{"learn":[0.4611953335],"iteration":574,"passed_time":3.621374004,"remaining_time":2.676667742},
{"learn":[0.4610661192],"iteration":575,"passed_time":3.626332032,"remaining_time":2.669383302},
{"learn":[0.4608139784],"iteration":576,"passed_time":3.63152427,"remaining_time":2.662278624},
{"learn":[0.4605147031],"iteration":577,"passed_time":3.636654415,"remaining_time":2.655135231},
{"learn":[0.460392508],"iteration":578,"passed_time":3.64164343,"remaining_time":2.647896172},
{"learn":[0.4602893704],"iteration":579,"passed_time":3.646668139,"remaining_time":2.640690721},
{"learn":[0.460247601],"iteration":580,"passed_time":3.65206149,"remaining_time":2.633758631},
{"learn":[0.4601709873],"iteration":581,"passed_time":3.657861908,"remaining_time":2.627124188},
{"learn":[0.4600029082],"iteration":582,"passed_time":3.662598195,"remaining_time":2.619731471},
{"learn":[0.4597803616],"iteration":583,"passed_time":3.668221416,"remaining_time":2.612979639},
{"learn":[0.4596772775],"iteration":584,"passed_time":3.673274372,"remaining_time":2.605827118},
{"learn":[0.4595686809],"iteration":585,"passed_time":3.678143861,"remaining_time":2.598552148},
{"learn":[0.4594201735],"iteration":586,"passed_time":3.683538572,"remaining_time":2.591654907},
{"learn":[0.4592530928],"iteration":587,"passed_time":3.689446996,"remaining_time":2.585122725},
{"learn":[0.4591082536],"iteration":588,"passed_time":3.694644152,"remaining_time":2.578096344},
{"learn":[0.4588427923],"iteration":589,"passed_time":3.700171896,"remaining_time":2.571305894},
{"learn":[0.4586484724],"iteration":590,"passed_time":3.705397329,"remaining_time":2.564310503},
{"learn":[0.4584658764],"iteration":591,"passed_time":3.710524285,"remaining_time":2.557253223},
{"learn":[0.4583599955],"iteration":592,"passed_time":3.715818569,"remaining_time":2.550317298},
{"learn":[0.4582431303],"iteration":593,"passed_time":3.720785316,"remaining_time":2.543163028},
{"learn":[0.4581049116],"iteration":594,"passed_time":3.726903412,"remaining_time":2.536799801},
{"learn":[0.4579710335],"iteration":595,"passed_time":3.731843423,"remaining_time":2.52963883},
{"learn":[0.4577482481],"iteration":596,"passed_time":3.737907056,"remaining_time":2.523243791},
{"learn":[0.4575444794],"iteration":597,"passed_time":3.742847166,"remaining_time":2.516094583},
{"learn":[0.4574483156],"iteration":598,"passed_time":3.748059601,"remaining_time":2.509135058},
{"learn":[0.4571973316],"iteration":599,"passed_time":3.753613531,"remaining_time":2.502409021},
{"learn":[0.4570386584],"iteration":600,"passed_time":3.758812647,"remaining_time":2.495451325},
{"learn":[0.4567484368],"iteration":601,"passed_time":3.764358368,"remaining_time":2.488728622},
{"learn":[0.4566082847],"iteration":602,"passed_time":3.769432851,"remaining_time":2.481699572},
{"learn":[0.456376076],"iteration":603,"passed_time":3.775893652,"remaining_time":2.475585904},
{"learn":[0.4561491065],"iteration":604,"passed_time":3.781554728,"remaining_time":2.468948955},
{"learn":[0.4560925902],"iteration":605,"passed_time":3.789772388,"remaining_time":2.463977427},
{"learn":[0.4559519746],"iteration":606,"passed_time":3.799846094,"remaining_time":2.460196894},
{"learn":[0.4557049409],"iteration":607,"passed_time":3.806308944,"remaining_time":2.454067609},
{"learn":[0.4553850139],"iteration":608,"passed_time":3.811580431,"remaining_time":2.447172329},
{"learn":[0.4552857367],"iteration":609,"passed_time":3.816671262,"remaining_time":2.440166872},
{"learn":[0.4551257963],"iteration":610,"passed_time":3.821604663,"remaining_time":2.433067453},
{"learn":[0.4550766434],"iteration":611,"passed_time":3.826514418,"remaining_time":2.425960121},
{"learn":[0.4548465039],"iteration":612,"passed_time":3.832624945,"remaining_time":2.419618032},
{"learn":[0.4545303135],"iteration":613,"passed_time":3.838229698,"remaining_time":2.412958735},
{"learn":[0.4542935683],"iteration":614,"passed_time":3.847627982,"remaining_time":2.40867768},
{"learn":[0.4542048862],"iteration":615,"passed_time":3.852860085,"remaining_time":2.40178291},
{"learn":[0.4540021026],"iteration":616,"passed_time":3.858718495,"remaining_time":2.395282307},
{"learn":[0.4539422678],"iteration":617,"passed_time":3.863554639,"remaining_time":2.388151897},
{"learn":[0.45383615],"iteration":618,"passed_time":3.869161852,"remaining_time":2.381503498},
{"learn":[0.4536218642],"iteration":619,"passed_time":3.874684546,"remaining_time":2.374806657},
{"learn":[0.4534496277],"iteration":620,"passed_time":3.879550206,"remaining_time":2.367712606},
{"learn":[0.4534075348],"iteration":621,"passed_time":3.884650046,"remaining_time":2.360768034},
{"learn":[0.4533165898],"iteration":622,"passed_time":3.889761924,"remaining_time":2.35383667},
{"learn":[0.4529637893],"iteration":623,"passed_time":3.894743469,"remaining_time":2.346832603},
{"learn":[0.4528150067],"iteration":624,"passed_time":3.899967382,"remaining_time":2.339980429},
{"learn":[0.4525903439],"iteration":625,"passed_time":3.905146352,"remaining_time":2.333106606},
{"learn":[0.4523514438],"iteration":626,"passed_time":3.910553621,"remaining_time":2.326374004},
{"learn":[0.4522526922],"iteration":627,"passed_time":3.915476014,"remaining_time":2.319358403},
{"learn":[0.4521084977],"iteration":628,"passed_time":3.920912759,"remaining_time":2.312652836},
{"learn":[0.4519565046],"iteration":629,"passed_time":3.927226219,"remaining_time":2.306466192},
{"learn":[0.4518337277],"iteration":630,"passed_time":3.932047805,"remaining_time":2.29940672},
{"learn":[0.4515845634],"iteration":631,"passed_time":3.937647829,"remaining_time":2.292807597},
{"learn":[0.451292294],"iteration":632,"passed_time":3.942390226,"remaining_time":2.285714396},
{"learn":[0.4511638954],"iteration":633,"passed_time":3.948233888,"remaining_time":2.279264358},
{"learn":[0.4509036797],"iteration":634,"passed_time":3.954015848,"remaining_time":2.272780763},
{"learn":[0.450823257],"iteration":635,"passed_time":3.961819682,"remaining_time":2.267456547},
{"learn":[0.4507315982],"iteration":636,"passed_time":3.967230731,"remaining_time":2.260760997},
{"learn":[0.4506333575],"iteration":637,"passed_time":3.972098831,"remaining_time":2.253761405},
{"learn":[0.4505736275],"iteration":638,"passed_time":3.977292808,"remaining_time":2.246952588},
{"learn":[0.4503514127],"iteration":639,"passed_time":3.982393967,"remaining_time":2.240096607},
{"learn":[0.4501835948],"iteration":640,"passed_time":3.988371472,"remaining_time":2.233736908},
{"learn":[0.4498797322],"iteration":641,"passed_time":3.993608963,"remaining_time":2.226965746},
{"learn":[0.4498268901],"iteration":642,"passed_time":3.998240654,"remaining_time":2.219863007},
{"learn":[0.4495813274],"iteration":643,"passed_time":4.004039482,"remaining_time":2.21341313},
{"learn":[0.4493699353],"iteration":644,"passed_time":4.009243458,"remaining_time":2.206637872},
{"learn":[0.4493011566],"iteration":645,"passed_time":4.013922163,"remaining_time":2.199579637},
{"learn":[0.4492103783],"iteration":646,"passed_time":4.018561933,"remaining_time":2.192507515},
{"learn":[0.4491446784],"iteration":647,"passed_time":4.023500504,"remaining_time":2.185605212},
{"learn":[0.4489863423],"iteration":648,"passed_time":4.029455711,"remaining_time":2.17925879},
{"learn":[0.4487522472],"iteration":649,"passed_time":4.034979515,"remaining_time":2.172681277},
{"learn":[0.4485081611],"iteration":650,"passed_time":4.040756375,"remaining_time":2.166242665},
{"learn":[0.4483076058],"iteration":651,"passed_time":4.045675829,"remaining_time":2.159348448},
{"learn":[0.4482120516],"iteration":652,"passed_time":4.050190975,"remaining_time":2.152245434},
{"learn":[0.4479988271],"iteration":653,"passed_time":4.0550225,"remaining_time":2.145317714},
{"learn":[0.447756994],"iteration":654,"passed_time":4.060858153,"remaining_time":2.138925287},
{"learn":[0.4474873086],"iteration":655,"passed_time":4.066041692,"remaining_time":2.132192594},
{"learn":[0.4473292409],"iteration":656,"passed_time":4.070826373,"remaining_time":2.125256386},
{"learn":[0.4472188374],"iteration":657,"passed_time":4.075531614,"remaining_time":2.118285429},
{"learn":[0.4469608356],"iteration":658,"passed_time":4.080864823,"remaining_time":2.111646289},
{"learn":[0.4469350289],"iteration":659,"passed_time":4.13178096,"remaining_time":2.128493222},
{"learn":[0.4467400144],"iteration":660,"passed_time":4.14988461,"remaining_time":2.128306933},
{"learn":[0.4465386404],"iteration":661,"passed_time":4.156770365,"remaining_time":2.122338948},
{"learn":[0.446421581],"iteration":662,"passed_time":4.1711902,"remaining_time":2.120197733},
{"learn":[0.4463481639],"iteration":663,"passed_time":4.176473805,"remaining_time":2.113396383},
{"learn":[0.4461780015],"iteration":664,"passed_time":4.181754381,"remaining_time":2.106598072},
{"learn":[0.4460917301],"iteration":665,"passed_time":4.189177735,"remaining_time":2.100878924},
{"learn":[0.4459443521],"iteration":666,"passed_time":4.194248429,"remaining_time":2.0939801},
{"learn":[0.4458078012],"iteration":667,"passed_time":4.198742598,"remaining_time":2.086800213},
{"learn":[0.4457328071],"iteration":668,"passed_time":4.203390427,"remaining_time":2.079704382},
{"learn":[0.445586082],"iteration":669,"passed_time":4.207738905,"remaining_time":2.072468416},
{"learn":[0.4453786678],"iteration":670,"passed_time":4.217394186,"remaining_time":2.067843051},
{"learn":[0.4453067291],"iteration":671,"passed_time":4.226092283,"remaining_time":2.062735519},
{"learn":[0.4451099742],"iteration":672,"passed_time":4.231265903,"remaining_time":2.055904829},
{"learn":[0.444998033],"iteration":673,"passed_time":4.236034756,"remaining_time":2.048883279},
{"learn":[0.444920116],"iteration":674,"passed_time":4.241075563,"remaining_time":2.041999345},
{"learn":[0.4448184666],"iteration":675,"passed_time":4.246201769,"remaining_time":2.035161795},
{"learn":[0.4446536319],"iteration":676,"passed_time":4.251449739,"remaining_time":2.028387394},
{"learn":[0.4445054463],"iteration":677,"passed_time":4.257505703,"remaining_time":2.022001234},
{"learn":[0.4442661529],"iteration":678,"passed_time":4.264057472,"remaining_time":2.01585044},
{"learn":[0.4441627693],"iteration":679,"passed_time":4.268919423,"remaining_time":2.008903258},
{"learn":[0.4439849476],"iteration":680,"passed_time":4.274294956,"remaining_time":2.002202777},
{"learn":[0.4438108654],"iteration":681,"passed_time":4.27981797,"remaining_time":1.995574948},
{"learn":[0.4436509206],"iteration":682,"passed_time":4.285156229,"remaining_time":1.988864604},
{"learn":[0.4434189278],"iteration":683,"passed_time":4.290937289,"remaining_time":1.982362841},
{"learn":[0.4431567024],"iteration":684,"passed_time":4.300997266,"remaining_time":1.97783086},
{"learn":[0.4428960548],"iteration":685,"passed_time":4.306563175,"remaining_time":1.97122571},
{"learn":[0.442780044],"iteration":686,"passed_time":4.329536405,"remaining_time":1.972554432},
{"learn":[0.4426284917],"iteration":687,"passed_time":4.334181634,"remaining_time":1.965500974},
{"learn":[0.4425407134],"iteration":688,"passed_time":4.339279934,"remaining_time":1.958659012},
{"learn":[0.4422900027],"iteration":689,"passed_time":4.344846132,"remaining_time":1.95203232},
{"learn":[0.4420129661],"iteration":690,"passed_time":4.354012247,"remaining_time":1.947018501},
{"learn":[0.441790997],"iteration":691,"passed_time":4.362100504,"remaining_time":1.941512941},
{"learn":[0.4416557406],"iteration":692,"passed_time":4.367220031,"remaining_time":1.934684776},
{"learn":[0.4414395913],"iteration":693,"passed_time":4.374765379,"remaining_time":1.928931133},
{"learn":[0.4413406604],"iteration":694,"passed_time":4.380259207,"remaining_time":1.922272026},
{"learn":[0.4411828934],"iteration":695,"passed_time":4.386123866,"remaining_time":1.91577824},
{"learn":[0.441057556],"iteration":696,"passed_time":4.391674457,"remaining_time":1.909149728},
{"learn":[0.4408115741],"iteration":697,"passed_time":4.397071827,"remaining_time":1.902458011},
{"learn":[0.4407259165],"iteration":698,"passed_time":4.403078498,"remaining_time":1.896032372},
{"learn":[0.4406327175],"iteration":699,"passed_time":4.409843658,"remaining_time":1.889932996},
{"learn":[0.4403607401],"iteration":700,"passed_time":4.415857638,"remaining_time":1.883511318},
{"learn":[0.4401334082],"iteration":701,"passed_time":4.421281825,"remaining_time":1.876840433},
{"learn":[0.4400142914],"iteration":702,"passed_time":4.426445446,"remaining_time":1.870063012},
{"learn":[0.4398945514],"iteration":703,"passed_time":4.431416003,"remaining_time":1.863209001},
{"learn":[0.4398246999],"iteration":704,"passed_time":4.436503744,"remaining_time":1.856409368},
{"learn":[0.4396199286],"iteration":705,"passed_time":4.442382831,"remaining_time":1.849944125},
{"learn":[0.4393877932],"iteration":706,"passed_time":4.450395878,"remaining_time":1.844364911},
{"learn":[0.4393526637],"iteration":707,"passed_time":4.455374593,"remaining_time":1.837527375},
{"learn":[0.4391833522],"iteration":708,"passed_time":4.460591797,"remaining_time":1.830792966},
{"learn":[0.4389883868],"iteration":709,"passed_time":4.465760988,"remaining_time":1.82404322},
{"learn":[0.4388910743],"iteration":710,"passed_time":4.470756011,"remaining_time":1.817227127},
{"learn":[0.4386215689],"iteration":711,"passed_time":4.475770982,"remaining_time":1.810424217},
{"learn":[0.438485388],"iteration":712,"passed_time":4.481160484,"remaining_time":1.803777081},
{"learn":[0.4383205788],"iteration":713,"passed_time":4.489734906,"remaining_time":1.79840922},
{"learn":[0.4380931177],"iteration":714,"passed_time":4.494517028,"remaining_time":1.791520773},
{"learn":[0.4379505143],"iteration":715,"passed_time":4.501539345,"remaining_time":1.785526779},
{"learn":[0.4377151554],"iteration":716,"passed_time":4.50674919,"remaining_time":1.778814534},
{"learn":[0.4375475851],"iteration":717,"passed_time":4.511980512,"remaining_time":1.772114909},
{"learn":[0.4374453417],"iteration":718,"passed_time":4.517784399,"remaining_time":1.765643138},
{"learn":[0.4373031699],"iteration":719,"passed_time":4.525673062,"remaining_time":1.759983969},
{"learn":[0.4371628439],"iteration":720,"passed_time":4.534769687,"remaining_time":1.754786051},
{"learn":[0.4369487225],"iteration":721,"passed_time":4.539552298,"remaining_time":1.747916259},
{"learn":[0.4368102585],"iteration":722,"passed_time":4.544867169,"remaining_time":1.741256163},
{"learn":[0.4367014034],"iteration":723,"passed_time":4.550091882,"remaining_time":1.734565414},
{"learn":[0.4365806573],"iteration":724,"passed_time":4.555732481,"remaining_time":1.728036458},
{"learn":[0.4364855485],"iteration":725,"passed_time":4.561414734,"remaining_time":1.721525671},
{"learn":[0.4363290491],"iteration":726,"passed_time":4.56813643,"remaining_time":1.71540749},
{"learn":[0.4361349822],"iteration":727,"passed_time":4.573676082,"remaining_time":1.708846009},
{"learn":[0.4360363943],"iteration":728,"passed_time":4.579503506,"remaining_time":1.702394308},
{"learn":[0.4360073767],"iteration":729,"passed_time":4.584430568,"remaining_time":1.695611306},
{"learn":[0.4358480696],"iteration":730,"passed_time":4.590999965,"remaining_time":1.689437744},
{"learn":[0.435672149],"iteration":731,"passed_time":4.597513119,"remaining_time":1.683242508},
{"learn":[0.4353754503],"iteration":732,"passed_time":4.60336093,"remaining_time":1.67680405},
{"learn":[0.4352205947],"iteration":733,"passed_time":4.612507768,"remaining_time":1.67156276},
{"learn":[0.4350880948],"iteration":734,"passed_time":4.619213566,"remaining_time":1.665430742},
{"learn":[0.434902361],"iteration":735,"passed_time":4.624727171,"remaining_time":1.658869529},
{"learn":[0.4347693174],"iteration":736,"passed_time":4.631997526,"remaining_time":1.652938059},
{"learn":[0.434543755],"iteration":737,"passed_time":4.637412064,"remaining_time":1.64634412},
{"learn":[0.4343612514],"iteration":738,"passed_time":4.642397509,"remaining_time":1.639601826},
{"learn":[0.4341122742],"iteration":739,"passed_time":4.648267937,"remaining_time":1.633175221},
{"learn":[0.4338645557],"iteration":740,"passed_time":4.654368165,"remaining_time":1.626830438},
{"learn":[0.4336432544],"iteration":741,"passed_time":4.660216236,"remaining_time":1.620398637},
{"learn":[0.4335053031],"iteration":742,"passed_time":4.666237995,"remaining_time":1.614028485},
{"learn":[0.4333296769],"iteration":743,"passed_time":4.672168785,"remaining_time":1.607627969},
{"learn":[0.4331870872],"iteration":744,"passed_time":4.676912002,"remaining_time":1.600822229},
{"learn":[0.433068479],"iteration":745,"passed_time":4.682116238,"remaining_time":1.594178987},
{"learn":[0.432868373],"iteration":746,"passed_time":4.687150786,"remaining_time":1.587482127},
{"learn":[0.4327651045],"iteration":747,"passed_time":4.692071539,"remaining_time":1.580751374},
{"learn":[0.4324956139],"iteration":748,"passed_time":4.69777013,"remaining_time":1.574286118},
{"learn":[0.4324314592],"iteration":749,"passed_time":4.716810267,"remaining_time":1.572270089},
{"learn":[0.4321661746],"iteration":750,"passed_time":4.724995461,"remaining_time":1.56660968},
{"learn":[0.4319266913],"iteration":751,"passed_time":4.730225054,"remaining_time":1.559967837},
{"learn":[0.4317315726],"iteration":752,"passed_time":4.735980277,"remaining_time":1.553502163},
{"learn":[0.4316153775],"iteration":753,"passed_time":4.741118832,"remaining_time":1.546837178},
{"learn":[0.4314552097],"iteration":754,"passed_time":4.747169336,"remaining_time":1.540472169},
{"learn":[0.4314187408],"iteration":755,"passed_time":4.758538522,"remaining_time":1.535824602},
{"learn":[0.4312693019],"iteration":756,"passed_time":4.763822377,"remaining_time":1.529205862},
{"learn":[0.4311772236],"iteration":757,"passed_time":4.770220726,"remaining_time":1.522946459},
{"learn":[0.4309756381],"iteration":758,"passed_time":4.776531456,"remaining_time":1.516658868},
{"learn":[0.4308954406],"iteration":759,"passed_time":4.781947655,"remaining_time":1.510088733},
{"learn":[0.4307888557],"iteration":760,"passed_time":4.78738025,"remaining_time":1.50352678},
{"learn":[0.4305788561],"iteration":761,"passed_time":4.79331402,"remaining_time":1.497124327},
{"learn":[0.4303648669],"iteration":762,"passed_time":4.803262663,"remaining_time":1.491970185},
{"learn":[0.4301409748],"iteration":763,"passed_time":4.808616419,"remaining_time":1.485384129},
{"learn":[0.4300803539],"iteration":764,"passed_time":4.814052014,"remaining_time":1.478826436},
{"learn":[0.4299696173],"iteration":765,"passed_time":4.818972598,"remaining_time":1.472114344},
{"learn":[0.4298141074],"iteration":766,"passed_time":4.83196404,"remaining_time":1.467858698},
{"learn":[0.4296290908],"iteration":767,"passed_time":4.83698219,"remaining_time":1.461171703},
{"learn":[0.4295024271],"iteration":768,"passed_time":4.84428891,"remaining_time":1.455176513},
{"learn":[0.429419144],"iteration":769,"passed_time":4.848991372,"remaining_time":1.44840002},
{"learn":[0.4292513773],"iteration":770,"passed_time":4.854192048,"remaining_time":1.441776886},
{"learn":[0.429188594],"iteration":771,"passed_time":4.858976339,"remaining_time":1.435034463},
{"learn":[0.4290521341],"iteration":772,"passed_time":4.863968153,"remaining_time":1.428358047},
{"learn":[0.4288952076],"iteration":773,"passed_time":4.869473829,"remaining_time":1.421836028},
{"learn":[0.4287243958],"iteration":774,"passed_time":4.874529634,"remaining_time":1.415186023},
{"learn":[0.4287047935],"iteration":775,"passed_time":4.883229311,"remaining_time":1.409591966},
{"learn":[0.4284617614],"iteration":776,"passed_time":4.889684832,"remaining_time":1.40334584},
{"learn":[0.4284038943],"iteration":777,"passed_time":4.894312844,"remaining_time":1.396577701},
{"learn":[0.4281920342],"iteration":778,"passed_time":4.898961893,"remaining_time":1.389821025},
{"learn":[0.4280962833],"iteration":779,"passed_time":4.904028107,"remaining_time":1.383187415},
{"learn":[0.427879902],"iteration":780,"passed_time":4.909206206,"remaining_time":1.376589192},
{"learn":[0.4276545156],"iteration":781,"passed_time":4.915130687,"remaining_time":1.370202672},
{"learn":[0.4275276988],"iteration":782,"passed_time":4.920144358,"remaining_time":1.363564912},
{"learn":[0.427471318],"iteration":783,"passed_time":4.924809255,"remaining_time":1.356835203},
{"learn":[0.4272301026],"iteration":784,"passed_time":4.929992064,"remaining_time":1.350252603},
{"learn":[0.4271448122],"iteration":785,"passed_time":4.93504334,"remaining_time":1.343637754},
{"learn":[0.4270021788],"iteration":786,"passed_time":4.940890541,"remaining_time":1.337242294},
{"learn":[0.4267812534],"iteration":787,"passed_time":4.946616598,"remaining_time":1.330815633},
{"learn":[0.4265719361],"iteration":788,"passed_time":4.957875968,"remaining_time":1.325870506},
{"learn":[0.4263701676],"iteration":789,"passed_time":4.964202117,"remaining_time":1.319598031},
{"learn":[0.4261349746],"iteration":790,"passed_time":4.970017852,"remaining_time":1.313190558},
{"learn":[0.4260322109],"iteration":791,"passed_time":4.974687888,"remaining_time":1.306483688},
{"learn":[0.4259532653],"iteration":792,"passed_time":4.982862364,"remaining_time":1.300696733},
{"learn":[0.4258496505],"iteration":793,"passed_time":4.987944836,"remaining_time":1.294101557},
{"learn":[0.4257027389],"iteration":794,"passed_time":4.992770411,"remaining_time":1.287443943},
{"learn":[0.4256507249],"iteration":795,"passed_time":4.997781713,"remaining_time":1.280838529},
{"learn":[0.4254940923],"iteration":796,"passed_time":5.004070526,"remaining_time":1.274562505},
{"learn":[0.4253622945],"iteration":797,"passed_time":5.009716094,"remaining_time":1.268123623},
{"learn":[0.4252542269],"iteration":798,"passed_time":5.015233659,"remaining_time":1.261654525},
{"learn":[0.4251498592],"iteration":799,"passed_time":5.020034978,"remaining_time":1.255008744},
{"learn":[0.4250332608],"iteration":800,"passed_time":5.026792079,"remaining_time":1.248853463},
{"learn":[0.4249684103],"iteration":801,"passed_time":5.03279991,"remaining_time":1.242511698},
{"learn":[0.4246888524],"iteration":802,"passed_time":5.038282059,"remaining_time":1.2360418},
{"learn":[0.4245179174],"iteration":803,"passed_time":5.04976167,"remaining_time":1.231036427},
{"learn":[0.4243836984],"iteration":804,"passed_time":5.054711939,"remaining_time":1.224433327},
{"learn":[0.4243351421],"iteration":805,"passed_time":5.059665458,"remaining_time":1.21783511},
{"learn":[0.4240585221],"iteration":806,"passed_time":5.065087635,"remaining_time":1.211353053},
{"learn":[0.4238863802],"iteration":807,"passed_time":5.070714306,"remaining_time":1.204922211},
{"learn":[0.42375084],"iteration":808,"passed_time":5.079448937,"remaining_time":1.199227129},
{"learn":[0.4236306409],"iteration":809,"passed_time":5.084856327,"remaining_time":1.192744077},
{"learn":[0.4234765017],"iteration":810,"passed_time":5.090513583,"remaining_time":1.186321908},
{"learn":[0.4232905839],"iteration":811,"passed_time":5.096328519,"remaining_time":1.17993813},
{"learn":[0.423118305],"iteration":812,"passed_time":5.102201777,"remaining_time":1.173569166},
{"learn":[0.42310712],"iteration":813,"passed_time":5.107284188,"remaining_time":1.167020711},
{"learn":[0.422908606],"iteration":814,"passed_time":5.112571173,"remaining_time":1.160522291},
{"learn":[0.4226066367],"iteration":815,"passed_time":5.118005919,"remaining_time":1.154060158},
{"learn":[0.4224315471],"iteration":816,"passed_time":5.123052226,"remaining_time":1.147513534},
{"learn":[0.4222967181],"iteration":817,"passed_time":5.129551901,"remaining_time":1.141293944},
{"learn":[0.4221549758],"iteration":818,"passed_time":5.13458444,"remaining_time":1.134749431},
{"learn":[0.4221190814],"iteration":819,"passed_time":5.14020972,"remaining_time":1.128338719},
{"learn":[0.4221019716],"iteration":820,"passed_time":5.146122433,"remaining_time":1.121992589},
{"learn":[0.4219469152],"iteration":821,"passed_time":5.152181697,"remaining_time":1.115679248},
{"learn":[0.4217591065],"iteration":822,"passed_time":5.160952754,"remaining_time":1.109949742},
{"learn":[0.4215789797],"iteration":823,"passed_time":5.169598807,"remaining_time":1.104186153},
{"learn":[0.4214629799],"iteration":824,"passed_time":5.175524088,"remaining_time":1.097838443},
{"learn":[0.4213589865],"iteration":825,"passed_time":5.180522311,"remaining_time":1.091296467},
{"learn":[0.4211775406],"iteration":826,"passed_time":5.185860489,"remaining_time":1.084829341},
{"learn":[0.4210657525],"iteration":827,"passed_time":5.191283087,"remaining_time":1.078382477},
{"learn":[0.4210199956],"iteration":828,"passed_time":5.196437729,"remaining_time":1.071882813},
{"learn":[0.4208132426],"iteration":829,"passed_time":5.203080846,"remaining_time":1.065691258},
{"learn":[0.4206308104],"iteration":830,"passed_time":5.208810683,"remaining_time":1.059312883},
{"learn":[0.4205337127],"iteration":831,"passed_time":5.214788317,"remaining_time":1.052986102},
{"learn":[0.4203769087],"iteration":832,"passed_time":5.221172628,"remaining_time":1.046741691},
{"learn":[0.4201748831],"iteration":833,"passed_time":5.227160041,"remaining_time":1.040417946},
{"learn":[0.4200766932],"iteration":834,"passed_time":5.237272991,"remaining_time":1.034910232},
{"learn":[0.419929035],"iteration":835,"passed_time":5.243981649,"remaining_time":1.028723673},
{"learn":[0.4198420345],"iteration":836,"passed_time":5.248495336,"remaining_time":1.022108411},
{"learn":[0.4197329529],"iteration":837,"passed_time":5.253599565,"remaining_time":1.015612326},
{"learn":[0.4195616751],"iteration":838,"passed_time":5.259486311,"remaining_time":1.009269721},
{"learn":[0.4193807553],"iteration":839,"passed_time":5.264326165,"remaining_time":1.002728793},
{"learn":[0.4191899496],"iteration":840,"passed_time":5.270110795,"remaining_time":0.9963705307},
{"learn":[0.419141511],"iteration":841,"passed_time":5.279167804,"remaining_time":0.9906276877},
{"learn":[0.4190229332],"iteration":842,"passed_time":5.284366571,"remaining_time":0.9841584242},
{"learn":[0.4187727399],"iteration":843,"passed_time":5.290290242,"remaining_time":0.9778261585},
{"learn":[0.418595666],"iteration":844,"passed_time":5.295624691,"remaining_time":0.9713867776},
{"learn":[0.4185230849],"iteration":845,"passed_time":5.300640701,"remaining_time":0.9648920426},
{"learn":[0.4183241261],"iteration":846,"passed_time":5.306776515,"remaining_time":0.9586030777},
{"learn":[0.4181498773],"iteration":847,"passed_time":5.312029914,"remaining_time":0.9521563054},
{"learn":[0.4180711738],"iteration":848,"passed_time":5.317824533,"remaining_time":0.9458086036},
{"learn":[0.4178916612],"iteration":849,"passed_time":5.32331891,"remaining_time":0.9394092195},
{"learn":[0.4177668203],"iteration":850,"passed_time":5.33252276,"remaining_time":0.9336614469},
{"learn":[0.4176423392],"iteration":851,"passed_time":5.337966315,"remaining_time":0.9272523646},
{"learn":[0.417467758],"iteration":852,"passed_time":5.348516798,"remaining_time":0.9217256381},
{"learn":[0.4173528521],"iteration":853,"passed_time":5.35534911,"remaining_time":0.9155514872},
{"learn":[0.4172014937],"iteration":854,"passed_time":5.36949931,"remaining_time":0.910616842},
{"learn":[0.4169619092],"iteration":855,"passed_time":5.374834628,"remaining_time":0.904177788},
{"learn":[0.4168562011],"iteration":856,"passed_time":5.380295781,"remaining_time":0.8977623064},
{"learn":[0.4167041568],"iteration":857,"passed_time":5.385946868,"remaining_time":0.8913804839},
{"learn":[0.4165196593],"iteration":858,"passed_time":5.391190089,"remaining_time":0.8849334138},
{"learn":[0.4163361873],"iteration":859,"passed_time":5.39642949,"remaining_time":0.8784885216},
{"learn":[0.4160482141],"iteration":860,"passed_time":5.402748659,"remaining_time":0.8722207475},
{"learn":[0.4159221521],"iteration":861,"passed_time":5.407750212,"remaining_time":0.8657419132},
{"learn":[0.4158282022],"iteration":862,"passed_time":5.413491947,"remaining_time":0.8593840055},
{"learn":[0.4156263915],"iteration":863,"passed_time":5.419721918,"remaining_time":0.853104376},
{"learn":[0.4155068316],"iteration":864,"passed_time":5.424907986,"remaining_time":0.8466619401},
{"learn":[0.4154169884],"iteration":865,"passed_time":5.432126647,"remaining_time":0.8405369177},
{"learn":[0.4152297134],"iteration":866,"passed_time":5.439282697,"remaining_time":0.8343997678},
{"learn":[0.4149669659],"iteration":867,"passed_time":5.446900545,"remaining_time":0.8283304977},
{"learn":[0.4148099169],"iteration":868,"passed_time":5.452748447,"remaining_time":0.8219908475},
{"learn":[0.4147707008],"iteration":869,"passed_time":5.458108652,"remaining_time":0.8155794537},
{"learn":[0.4145730648],"iteration":870,"passed_time":5.463991749,"remaining_time":0.8092479168},
{"learn":[0.414515262],"iteration":871,"passed_time":5.468951717,"remaining_time":0.8027819034},
{"learn":[0.4144944135],"iteration":872,"passed_time":5.476115725,"remaining_time":0.7966399737},
{"learn":[0.4144058161],"iteration":873,"passed_time":5.482905222,"remaining_time":0.790441714},
{"learn":[0.4143344892],"iteration":874,"passed_time":5.487882468,"remaining_time":0.7839832097},
{"learn":[0.4141258824],"iteration":875,"passed_time":5.49327152,"remaining_time":0.7775863795},
{"learn":[0.414020536],"iteration":876,"passed_time":5.501829865,"remaining_time":0.7716363436},
{"learn":[0.4138631512],"iteration":877,"passed_time":5.507073575,"remaining_time":0.7652197907},
{"learn":[0.4137185718],"iteration":878,"passed_time":5.513450227,"remaining_time":0.7589618629},
{"learn":[0.4135455994],"iteration":879,"passed_time":5.519617926,"remaining_time":0.7526751718},
{"learn":[0.4135005361],"iteration":880,"passed_time":5.524480987,"remaining_time":0.7462125284},
{"learn":[0.4134213406],"iteration":881,"passed_time":5.529463182,"remaining_time":0.7397694507},
{"learn":[0.4132147592],"iteration":882,"passed_time":5.535126348,"remaining_time":0.7334199125},
{"learn":[0.413075208],"iteration":883,"passed_time":5.540541446,"remaining_time":0.7270393753},
{"learn":[0.4129826285],"iteration":884,"passed_time":5.545287822,"remaining_time":0.7205741238},
{"learn":[0.4128392297],"iteration":885,"passed_time":5.55063076,"remaining_time":0.7141895109},
{"learn":[0.4126928702],"iteration":886,"passed_time":5.555630143,"remaining_time":0.7077634793},
{"learn":[0.4124616036],"iteration":887,"passed_time":5.561104893,"remaining_time":0.7014006171},
{"learn":[0.4123557886],"iteration":888,"passed_time":5.566426683,"remaining_time":0.6950206545},
{"learn":[0.4121295699],"iteration":889,"passed_time":5.572344635,"remaining_time":0.6887167527},
{"learn":[0.4120598934],"iteration":890,"passed_time":5.581908178,"remaining_time":0.6828596986},
{"learn":[0.4118973877],"iteration":891,"passed_time":5.586487716,"remaining_time":0.6763908894},
{"learn":[0.4117797761],"iteration":892,"passed_time":5.59102531,"remaining_time":0.6699212857},
{"learn":[0.4116687414],"iteration":893,"passed_time":5.596707733,"remaining_time":0.6635917446},
{"learn":[0.4115445307],"iteration":894,"passed_time":5.601999417,"remaining_time":0.6572178087},
{"learn":[0.4114826046],"iteration":895,"passed_time":5.606851589,"remaining_time":0.6507952738},
{"learn":[0.4113822862],"iteration":896,"passed_time":5.618882138,"remaining_time":0.6452005131},
{"learn":[0.4111944924],"iteration":897,"passed_time":5.624669487,"remaining_time":0.6388822803},
{"learn":[0.4111103562],"iteration":898,"passed_time":5.630367228,"remaining_time":0.6325551614},
{"learn":[0.4109249337],"iteration":899,"passed_time":5.635558846,"remaining_time":0.6261732051},
{"learn":[0.4108528206],"iteration":900,"passed_time":5.640534442,"remaining_time":0.6197701551},
{"learn":[0.4108175376],"iteration":901,"passed_time":5.645674336,"remaining_time":0.6133881208},
{"learn":[0.4106158878],"iteration":902,"passed_time":5.650885401,"remaining_time":0.6070164827},
{"learn":[0.4105110176],"iteration":903,"passed_time":5.656716165,"remaining_time":0.600713221},
{"learn":[0.4103858973],"iteration":904,"passed_time":5.661517264,"remaining_time":0.5943029172},
{"learn":[0.4102623634],"iteration":905,"passed_time":5.666845043,"remaining_time":0.5879508102},
{"learn":[0.410153437],"iteration":906,"passed_time":5.672538755,"remaining_time":0.5816384831},
{"learn":[0.4100230248],"iteration":907,"passed_time":5.677616247,"remaining_time":0.5752650823},
{"learn":[0.4099565011],"iteration":908,"passed_time":5.683250647,"remaining_time":0.5689502848},
{"learn":[0.4099137942],"iteration":909,"passed_time":5.688152182,"remaining_time":0.5625645015},
{"learn":[0.4097201604],"iteration":910,"passed_time":5.694352677,"remaining_time":0.5563088785},
{"learn":[0.4096341711],"iteration":911,"passed_time":5.699342111,"remaining_time":0.5499365195},
{"learn":[0.4095052048],"iteration":912,"passed_time":5.705241206,"remaining_time":0.5436538718},
{"learn":[0.4093402674],"iteration":913,"passed_time":5.710245658,"remaining_time":0.5372878847},
{"learn":[0.4092997095],"iteration":914,"passed_time":5.715293195,"remaining_time":0.530928876},
{"learn":[0.4092679803],"iteration":915,"passed_time":5.720708243,"remaining_time":0.5246064327},
{"learn":[0.4091612813],"iteration":916,"passed_time":5.725867155,"remaining_time":0.518262785},
{"learn":[0.409076326],"iteration":917,"passed_time":5.731869166,"remaining_time":0.5119970279},
{"learn":[0.4088954561],"iteration":918,"passed_time":5.736923311,"remaining_time":0.5056483006},
{"learn":[0.408826429],"iteration":919,"passed_time":5.745641555,"remaining_time":0.4996210048},
{"learn":[0.4086015192],"iteration":920,"passed_time":5.750976564,"remaining_time":0.493297664},
{"learn":[0.4085098095],"iteration":921,"passed_time":5.756324721,"remaining_time":0.4869775794},
{"learn":[0.4082900661],"iteration":922,"passed_time":5.761943262,"remaining_time":0.4806821573},
{"learn":[0.408209487],"iteration":923,"passed_time":5.767270592,"remaining_time":0.4743642478},
{"learn":[0.4080762342],"iteration":924,"passed_time":5.772662413,"remaining_time":0.4680537092},
{"learn":[0.407944828],"iteration":925,"passed_time":5.777812386,"remaining_time":0.4617258279},
{"learn":[0.4076891318],"iteration":926,"passed_time":5.783346339,"remaining_time":0.4554307257},
{"learn":[0.4075441597],"iteration":927,"passed_time":5.788541676,"remaining_time":0.4491109921},
{"learn":[0.4074704705],"iteration":928,"passed_time":5.793640236,"remaining_time":0.4427862828},
{"learn":[0.4073875134],"iteration":929,"passed_time":5.798049496,"remaining_time":0.4364123277},
{"learn":[0.4073029025],"iteration":930,"passed_time":5.802793173,"remaining_time":0.430067378},
{"learn":[0.407179791],"iteration":931,"passed_time":5.807459649,"remaining_time":0.4237202319},
{"learn":[0.4070780349],"iteration":932,"passed_time":5.812465911,"remaining_time":0.417401089},
{"learn":[0.4069402456],"iteration":933,"passed_time":5.817845564,"remaining_time":0.4111111426},
{"learn":[0.406761629],"iteration":934,"passed_time":5.823482313,"remaining_time":0.4048410164},
{"learn":[0.406658225],"iteration":935,"passed_time":5.82844994,"remaining_time":0.3985264916},
{"learn":[0.4065339242],"iteration":936,"passed_time":5.833692731,"remaining_time":0.3922333426},
{"learn":[0.4064013706],"iteration":937,"passed_time":5.83894536,"remaining_time":0.3859430835},
{"learn":[0.4062001107],"iteration":938,"passed_time":5.845079024,"remaining_time":0.3797122689},
{"learn":[0.4061818612],"iteration":939,"passed_time":5.849816081,"remaining_time":0.3733925158},
{"learn":[0.4061108326],"iteration":940,"passed_time":5.854806235,"remaining_time":0.3670919956},
{"learn":[0.4061025863],"iteration":941,"passed_time":5.859158253,"remaining_time":0.3607549668},
{"learn":[0.4059440736],"iteration":942,"passed_time":5.864457707,"remaining_time":0.354479416},
{"learn":[0.405778186],"iteration":943,"passed_time":5.874127746,"remaining_time":0.3484652052},
{"learn":[0.4057210927],"iteration":944,"passed_time":5.879408891,"remaining_time":0.3421878191},
{"learn":[0.4055967115],"iteration":945,"passed_time":5.884495223,"remaining_time":0.3359014186},
{"learn":[0.4055586331],"iteration":946,"passed_time":5.889262216,"remaining_time":0.3295996805},
{"learn":[0.4055115322],"iteration":947,"passed_time":5.894604284,"remaining_time":0.3233327244},
{"learn":[0.4053967433],"iteration":948,"passed_time":5.89950343,"remaining_time":0.3170439146},
{"learn":[0.4053485299],"iteration":949,"passed_time":5.904210781,"remaining_time":0.3107479358},
{"learn":[0.4051846687],"iteration":950,"passed_time":5.909688771,"remaining_time":0.304495005},
{"learn":[0.4050788001],"iteration":951,"passed_time":5.914752425,"remaining_time":0.2982228114},
{"learn":[0.4050133127],"iteration":952,"passed_time":5.919310346,"remaining_time":0.2919282122},
{"learn":[0.4049140584],"iteration":953,"passed_time":5.924332676,"remaining_time":0.2856596469},
{"learn":[0.4047036056],"iteration":954,"passed_time":5.93046241,"remaining_time":0.2794458727},
{"learn":[0.4045454152],"iteration":955,"passed_time":5.935521205,"remaining_time":0.2731829843},
{"learn":[0.4043561576],"iteration":956,"passed_time":5.940645732,"remaining_time":0.2669255658},
{"learn":[0.4042981391],"iteration":957,"passed_time":5.945944545,"remaining_time":0.2606781533},
{"learn":[0.4041451471],"iteration":958,"passed_time":5.950860059,"remaining_time":0.254416332},
{"learn":[0.4040949384],"iteration":959,"passed_time":5.956304193,"remaining_time":0.2481793414},
{"learn":[0.4038994934],"iteration":960,"passed_time":5.961325213,"remaining_time":0.2419268297},
{"learn":[0.4037732528],"iteration":961,"passed_time":5.966764138,"remaining_time":0.2356933859},
{"learn":[0.4035670158],"iteration":962,"passed_time":5.971994041,"remaining_time":0.2294535613},
{"learn":[0.4033740475],"iteration":963,"passed_time":5.977016911,"remaining_time":0.2232081004},
{"learn":[0.4033280743],"iteration":964,"passed_time":5.981877772,"remaining_time":0.2169592974},
{"learn":[0.4032849412],"iteration":965,"passed_time":5.986816492,"remaining_time":0.2107161084},
{"learn":[0.4031816569],"iteration":966,"passed_time":5.991988333,"remaining_time":0.2044835729},
{"learn":[0.4030806101],"iteration":967,"passed_time":5.997159723,"remaining_time":0.198253214},
{"learn":[0.4030318352],"iteration":968,"passed_time":6.001925586,"remaining_time":0.1920120673},
{"learn":[0.4028220751],"iteration":969,"passed_time":6.006735684,"remaining_time":0.1857753304},
{"learn":[0.4026941572],"iteration":970,"passed_time":6.012651656,"remaining_time":0.1795745603},
{"learn":[0.4026155343],"iteration":971,"passed_time":6.017694003,"remaining_time":0.17334921},
{"learn":[0.4025515214],"iteration":972,"passed_time":6.023607206,"remaining_time":0.1671504569},
{"learn":[0.4024808188],"iteration":973,"passed_time":6.0288241,"remaining_time":0.1609337029},
{"learn":[0.4023875956],"iteration":974,"passed_time":6.033358864,"remaining_time":0.1547015093},
{"learn":[0.4022844126],"iteration":975,"passed_time":6.038436267,"remaining_time":0.1484861377},
{"learn":[0.4022100501],"iteration":976,"passed_time":6.043917026,"remaining_time":0.1422825912},
{"learn":[0.4019901543],"iteration":977,"passed_time":6.04913599,"remaining_time":0.1360746337},
{"learn":[0.40182459],"iteration":978,"passed_time":6.054429655,"remaining_time":0.129870299},
{"learn":[0.4017335817],"iteration":979,"passed_time":6.059166962,"remaining_time":0.1236564686},
{"learn":[0.4016359859],"iteration":980,"passed_time":6.064195461,"remaining_time":0.1174512882},
{"learn":[0.4016144727],"iteration":981,"passed_time":6.068832781,"remaining_time":0.1112413341},
{"learn":[0.4014234256],"iteration":982,"passed_time":6.074085231,"remaining_time":0.1050452176},
{"learn":[0.4012723777],"iteration":983,"passed_time":6.079820307,"remaining_time":0.09885886678},
{"learn":[0.4010963221],"iteration":984,"passed_time":6.085297507,"remaining_time":0.09266950518},
{"learn":[0.4009206433],"iteration":985,"passed_time":6.091654841,"remaining_time":0.08649408497},
{"learn":[0.4007360861],"iteration":986,"passed_time":6.096804134,"remaining_time":0.08030238475},
{"learn":[0.4006980374],"iteration":987,"passed_time":6.101603153,"remaining_time":0.07410854033},
{"learn":[0.4006209316],"iteration":988,"passed_time":6.106967118,"remaining_time":0.0679238001},
{"learn":[0.4005497902],"iteration":989,"passed_time":6.111917118,"remaining_time":0.06173653654},
{"learn":[0.4004603152],"iteration":990,"passed_time":6.117420224,"remaining_time":0.05555679316},
{"learn":[0.400367162],"iteration":991,"passed_time":6.124124833,"remaining_time":0.04938810349},
{"learn":[0.4002754299],"iteration":992,"passed_time":6.129003172,"remaining_time":0.04320546042},
{"learn":[0.4001821685],"iteration":993,"passed_time":6.134040849,"remaining_time":0.03702640352},
{"learn":[0.3999928802],"iteration":994,"passed_time":6.140514449,"remaining_time":0.03085685653},
{"learn":[0.3997851706],"iteration":995,"passed_time":6.145648804,"remaining_time":0.0246813205},
{"learn":[0.3997500864],"iteration":996,"passed_time":6.150615171,"remaining_time":0.01850736762},
{"learn":[0.3996163882],"iteration":997,"passed_time":6.15769493,"remaining_time":0.01234007},
{"learn":[0.3995008506],"iteration":998,"passed_time":6.16248716,"remaining_time":0.006168655816},
{"learn":[0.3994643845],"iteration":999,"passed_time":6.167763527,"remaining_time":0}
]}